{
  "date": "2025-12-02",
  "total_events": 10,
  "new_events": 0,
  "platforms": {
    "jiuyangongshe": 1,
    "investing": 1,
    "eastmoney": 8
  },
  "events": [
    {
      "platform": "jiuyangongshe",
      "event_id": "jygs_24fb52f6c256442aaf91486b928a7e86_edf41806e6314411b2e0b0d6c811b010_20251202",
      "original_id": "24fb52f6c256442aaf91486b928a7e86",
      "event_date": "2025-12-02",
      "event_time": null,
      "event_datetime": null,
      "title": "2025亚洲电视论坛",
      "content": "",
      "category": null,
      "importance": 1,
      "country": "中国",
      "city": null,
      "stocks": [],
      "concepts": [],
      "themes": [],
      "data_status": "ACTIVE",
      "is_new": false,
      "discovery_date": "2025-11-08",
      "raw_data": {
        "article_id": "24fb52f6c256442aaf91486b928a7e86",
        "user_id": "1",
        "title": "2025亚洲电视论坛",
        "content": "",
        "like_count": 0,
        "comment_count": 0,
        "forward_count": 0,
        "is_like": 0,
        "is_step": 0,
        "user": {
          "user_id": "1",
          "nickname": "韭菜团子"
        },
        "timeline": {
          "article_id": "24fb52f6c256442aaf91486b928a7e86",
          "timeline_id": "edf41806e6314411b2e0b0d6c811b010",
          "date": "2025-12-02",
          "grade": 6,
          "source": "2",
          "create_time": "2025-11-04 23:19:31",
          "theme_list": []
        }
      },
      "created_at": "2025-11-08T00:48:49.107129"
    },
    {
      "platform": "investing",
      "event_id": "inv__20251202010000",
      "original_id": "eventRowId_532296",
      "event_date": "2025-12-02",
      "event_time": "01:00",
      "event_datetime": "2025/12/02 01:00:00",
      "title": "亚特兰大联储GDPNow经济增长预测  (第四季度)",
      "content": null,
      "category": null,
      "importance": 2,
      "country": "美国",
      "city": null,
      "stocks": [],
      "concepts": [],
      "themes": [],
      "data_status": "ACTIVE",
      "is_new": false,
      "discovery_date": "2025-11-08",
      "raw_data": {
        "event_id": "eventRowId_532296",
        "event_attr_id": "",
        "datetime": "2025/12/02 01:00:00",
        "time": "01:00",
        "country": "美国",
        "importance": 2,
        "event_name": "亚特兰大联储GDPNow经济增长预测  (第四季度)"
      },
      "created_at": "2025-11-08T00:48:56.944942"
    },
    {
      "platform": "eastmoney",
      "event_id": "em_jjsj_20251202000000_-8586899734609955981",
      "original_id": "2025-12-02 00:00:00_中国香港：港口货物吞吐量：当季同比(报告期:2025年09月)",
      "event_date": "2025-12-02",
      "event_time": null,
      "event_datetime": "2025-12-02 00:00:00",
      "title": "中国香港：港口货物吞吐量：当季同比(报告期:2025年09月)",
      "content": null,
      "category": "经济数据",
      "importance": 4,
      "country": "中国香港",
      "city": null,
      "stocks": [],
      "concepts": [],
      "themes": [],
      "data_status": "ACTIVE",
      "is_new": false,
      "discovery_date": "2025-11-08",
      "raw_data": {
        "Name": "中国香港：港口货物吞吐量：当季同比(报告期:2025年09月)",
        "City": "中国香港"
      },
      "created_at": "2025-11-08T00:49:03.141247"
    },
    {
      "platform": "eastmoney",
      "event_id": "em_jjsj_20251202000000_-8619212524052617973",
      "original_id": "2025-12-02 00:00:00_韩国：CPI：同比(报告期:2025年11月)",
      "event_date": "2025-12-02",
      "event_time": null,
      "event_datetime": "2025-12-02 00:00:00",
      "title": "韩国：CPI：同比(报告期:2025年11月)",
      "content": null,
      "category": "经济数据",
      "importance": 4,
      "country": "韩国",
      "city": null,
      "stocks": [],
      "concepts": [],
      "themes": [],
      "data_status": "ACTIVE",
      "is_new": false,
      "discovery_date": "2025-11-08",
      "raw_data": {
        "Name": "韩国：CPI：同比(报告期:2025年11月)",
        "City": "韩国"
      },
      "created_at": "2025-11-08T00:49:03.141255"
    },
    {
      "platform": "eastmoney",
      "event_id": "em_jjsj_20251202000000_2405669696826053825",
      "original_id": "2025-12-02 00:00:00_菲律宾：PPI：同比(报告期:2025年10月)",
      "event_date": "2025-12-02",
      "event_time": null,
      "event_datetime": "2025-12-02 00:00:00",
      "title": "菲律宾：PPI：同比(报告期:2025年10月)",
      "content": null,
      "category": "经济数据",
      "importance": 4,
      "country": "菲律宾",
      "city": null,
      "stocks": [],
      "concepts": [],
      "themes": [],
      "data_status": "ACTIVE",
      "is_new": false,
      "discovery_date": "2025-11-08",
      "raw_data": {
        "Name": "菲律宾：PPI：同比(报告期:2025年10月)",
        "City": "菲律宾"
      },
      "created_at": "2025-11-08T00:49:03.141262"
    },
    {
      "platform": "eastmoney",
      "event_id": "em_jjsj_20251202093000_251570217040253715",
      "original_id": "2025-12-02 09:30:00_澳大利亚：经常项目差额(报告期:2025年09月)",
      "event_date": "2025-12-02",
      "event_time": "09:30:00",
      "event_datetime": "2025-12-02 09:30:00",
      "title": "澳大利亚：经常项目差额(报告期:2025年09月)",
      "content": null,
      "category": "经济数据",
      "importance": 4,
      "country": "澳大利亚",
      "city": null,
      "stocks": [],
      "concepts": [],
      "themes": [],
      "data_status": "ACTIVE",
      "is_new": false,
      "discovery_date": "2025-11-08",
      "raw_data": {
        "Name": "澳大利亚：经常项目差额(报告期:2025年09月)",
        "City": "澳大利亚"
      },
      "created_at": "2025-11-08T00:49:03.141270"
    },
    {
      "platform": "eastmoney",
      "event_id": "em_jjsj_20251202180000_-2463463702731023979",
      "original_id": "2025-12-02 18:00:00_德国：失业率：季调(报告期:2025年10月)",
      "event_date": "2025-12-02",
      "event_time": "18:00:00",
      "event_datetime": "2025-12-02 18:00:00",
      "title": "德国：失业率：季调(报告期:2025年10月)",
      "content": null,
      "category": "经济数据",
      "importance": 4,
      "country": "德国",
      "city": null,
      "stocks": [],
      "concepts": [],
      "themes": [],
      "data_status": "ACTIVE",
      "is_new": false,
      "discovery_date": "2025-11-08",
      "raw_data": {
        "Name": "德国：失业率：季调(报告期:2025年10月)",
        "City": "德国"
      },
      "created_at": "2025-11-08T00:49:03.141280"
    },
    {
      "platform": "eastmoney",
      "event_id": "em_jjsj_20251202180000_1973708384843920915",
      "original_id": "2025-12-02 18:00:00_意大利：失业率：季调(报告期:2025年10月)",
      "event_date": "2025-12-02",
      "event_time": "18:00:00",
      "event_datetime": "2025-12-02 18:00:00",
      "title": "意大利：失业率：季调(报告期:2025年10月)",
      "content": null,
      "category": "经济数据",
      "importance": 4,
      "country": "意大利",
      "city": null,
      "stocks": [],
      "concepts": [],
      "themes": [],
      "data_status": "ACTIVE",
      "is_new": false,
      "discovery_date": "2025-11-08",
      "raw_data": {
        "Name": "意大利：失业率：季调(报告期:2025年10月)",
        "City": "意大利"
      },
      "created_at": "2025-11-08T00:49:03.141287"
    },
    {
      "platform": "eastmoney",
      "event_id": "em_jjsj_20251202180000_3880581042051743409",
      "original_id": "2025-12-02 18:00:00_意大利：失业人数：季调(报告期:2025年10月)",
      "event_date": "2025-12-02",
      "event_time": "18:00:00",
      "event_datetime": "2025-12-02 18:00:00",
      "title": "意大利：失业人数：季调(报告期:2025年10月)",
      "content": null,
      "category": "经济数据",
      "importance": 4,
      "country": "意大利",
      "city": null,
      "stocks": [],
      "concepts": [],
      "themes": [],
      "data_status": "ACTIVE",
      "is_new": false,
      "discovery_date": "2025-11-08",
      "raw_data": {
        "Name": "意大利：失业人数：季调(报告期:2025年10月)",
        "City": "意大利"
      },
      "created_at": "2025-11-08T00:49:03.141295"
    },
    {
      "platform": "eastmoney",
      "event_id": "em_jjsj_20251202180000_-683223706904005552",
      "original_id": "2025-12-02 18:00:00_欧盟27国：失业率：季调(报告期:2025年10月)",
      "event_date": "2025-12-02",
      "event_time": "18:00:00",
      "event_datetime": "2025-12-02 18:00:00",
      "title": "欧盟27国：失业率：季调(报告期:2025年10月)",
      "content": null,
      "category": "经济数据",
      "importance": 4,
      "country": "欧盟",
      "city": null,
      "stocks": [],
      "concepts": [],
      "themes": [],
      "data_status": "ACTIVE",
      "is_new": false,
      "discovery_date": "2025-11-08",
      "raw_data": {
        "Name": "欧盟27国：失业率：季调(报告期:2025年10月)",
        "City": "欧盟"
      },
      "created_at": "2025-11-08T00:49:03.141305"
    }
  ]
}