{
  "date": "2025-12-17",
  "total_events": 9,
  "new_events": 9,
  "platforms": {
    "eastmoney": 9
  },
  "events": [
    {
      "platform": "eastmoney",
      "event_id": "em_jjsj_20251217075000_-7126490535986634371",
      "original_id": "2025-12-17 07:50:00_日本：贸易差额：当月值(报告期:2025年11月)",
      "event_date": "2025-12-17",
      "event_time": "07:50:00",
      "event_datetime": "2025-12-17 07:50:00",
      "title": "日本：贸易差额：当月值(报告期:2025年11月)",
      "content": null,
      "category": "经济数据",
      "importance": 4,
      "country": "日本",
      "city": null,
      "stocks": [],
      "concepts": [],
      "themes": [],
      "data_status": "ACTIVE",
      "is_new": true,
      "discovery_date": "2025-10-04",
      "raw_data": {
        "Name": "日本：贸易差额：当月值(报告期:2025年11月)",
        "City": "日本"
      },
      "created_at": "2025-10-04T00:45:14.976237"
    },
    {
      "platform": "eastmoney",
      "event_id": "em_jjsj_20251217075000_6373959219179157146",
      "original_id": "2025-12-17 07:50:00_日本：出口金额：当月值(报告期:2025年11月)",
      "event_date": "2025-12-17",
      "event_time": "07:50:00",
      "event_datetime": "2025-12-17 07:50:00",
      "title": "日本：出口金额：当月值(报告期:2025年11月)",
      "content": null,
      "category": "经济数据",
      "importance": 4,
      "country": "日本",
      "city": null,
      "stocks": [],
      "concepts": [],
      "themes": [],
      "data_status": "ACTIVE",
      "is_new": true,
      "discovery_date": "2025-10-04",
      "raw_data": {
        "Name": "日本：出口金额：当月值(报告期:2025年11月)",
        "City": "日本"
      },
      "created_at": "2025-10-04T00:45:14.976244"
    },
    {
      "platform": "eastmoney",
      "event_id": "em_jjsj_20251217075000_-7364502378755352153",
      "original_id": "2025-12-17 07:50:00_日本：进口金额：当月值(报告期:2025年11月)",
      "event_date": "2025-12-17",
      "event_time": "07:50:00",
      "event_datetime": "2025-12-17 07:50:00",
      "title": "日本：进口金额：当月值(报告期:2025年11月)",
      "content": null,
      "category": "经济数据",
      "importance": 4,
      "country": "日本",
      "city": null,
      "stocks": [],
      "concepts": [],
      "themes": [],
      "data_status": "ACTIVE",
      "is_new": true,
      "discovery_date": "2025-10-04",
      "raw_data": {
        "Name": "日本：进口金额：当月值(报告期:2025年11月)",
        "City": "日本"
      },
      "created_at": "2025-10-04T00:45:14.976251"
    },
    {
      "platform": "eastmoney",
      "event_id": "em_jjsj_20251217180000_-4274283588622968017",
      "original_id": "2025-12-17 18:00:00_意大利：HICP：环比(报告期:2025年11月)",
      "event_date": "2025-12-17",
      "event_time": "18:00:00",
      "event_datetime": "2025-12-17 18:00:00",
      "title": "意大利：HICP：环比(报告期:2025年11月)",
      "content": null,
      "category": "经济数据",
      "importance": 4,
      "country": "意大利",
      "city": null,
      "stocks": [],
      "concepts": [],
      "themes": [],
      "data_status": "ACTIVE",
      "is_new": true,
      "discovery_date": "2025-10-04",
      "raw_data": {
        "Name": "意大利：HICP：环比(报告期:2025年11月)",
        "City": "意大利"
      },
      "created_at": "2025-10-04T00:45:14.976259"
    },
    {
      "platform": "eastmoney",
      "event_id": "em_jjsj_20251217180000_-284377949790217006",
      "original_id": "2025-12-17 18:00:00_意大利：HICP：同比(报告期:2025年11月)",
      "event_date": "2025-12-17",
      "event_time": "18:00:00",
      "event_datetime": "2025-12-17 18:00:00",
      "title": "意大利：HICP：同比(报告期:2025年11月)",
      "content": null,
      "category": "经济数据",
      "importance": 4,
      "country": "意大利",
      "city": null,
      "stocks": [],
      "concepts": [],
      "themes": [],
      "data_status": "ACTIVE",
      "is_new": true,
      "discovery_date": "2025-10-04",
      "raw_data": {
        "Name": "意大利：HICP：同比(报告期:2025年11月)",
        "City": "意大利"
      },
      "created_at": "2025-10-04T00:45:14.976265"
    },
    {
      "platform": "eastmoney",
      "event_id": "em_jjsj_20251217180000_4289690140504628984",
      "original_id": "2025-12-17 18:00:00_德国：HICP：同比(报告期:2025年11月)",
      "event_date": "2025-12-17",
      "event_time": "18:00:00",
      "event_datetime": "2025-12-17 18:00:00",
      "title": "德国：HICP：同比(报告期:2025年11月)",
      "content": null,
      "category": "经济数据",
      "importance": 4,
      "country": "德国",
      "city": null,
      "stocks": [],
      "concepts": [],
      "themes": [],
      "data_status": "ACTIVE",
      "is_new": true,
      "discovery_date": "2025-10-04",
      "raw_data": {
        "Name": "德国：HICP：同比(报告期:2025年11月)",
        "City": "德国"
      },
      "created_at": "2025-10-04T00:45:14.976273"
    },
    {
      "platform": "eastmoney",
      "event_id": "em_jjsj_20251217180000_6752419216956166385",
      "original_id": "2025-12-17 18:00:00_德国：HICP：环比(报告期:2025年11月)",
      "event_date": "2025-12-17",
      "event_time": "18:00:00",
      "event_datetime": "2025-12-17 18:00:00",
      "title": "德国：HICP：环比(报告期:2025年11月)",
      "content": null,
      "category": "经济数据",
      "importance": 4,
      "country": "德国",
      "city": null,
      "stocks": [],
      "concepts": [],
      "themes": [],
      "data_status": "ACTIVE",
      "is_new": true,
      "discovery_date": "2025-10-04",
      "raw_data": {
        "Name": "德国：HICP：环比(报告期:2025年11月)",
        "City": "德国"
      },
      "created_at": "2025-10-04T00:45:14.976281"
    },
    {
      "platform": "eastmoney",
      "event_id": "em_jjsj_20251217180000_1411677222574384383",
      "original_id": "2025-12-17 18:00:00_欧元区：CPI：当月同比(报告期:2025年11月)",
      "event_date": "2025-12-17",
      "event_time": "18:00:00",
      "event_datetime": "2025-12-17 18:00:00",
      "title": "欧元区：CPI：当月同比(报告期:2025年11月)",
      "content": null,
      "category": "经济数据",
      "importance": 4,
      "country": "欧盟",
      "city": null,
      "stocks": [],
      "concepts": [],
      "themes": [],
      "data_status": "ACTIVE",
      "is_new": true,
      "discovery_date": "2025-10-04",
      "raw_data": {
        "Name": "欧元区：CPI：当月同比(报告期:2025年11月)",
        "City": "欧盟"
      },
      "created_at": "2025-10-04T00:45:14.976289"
    },
    {
      "platform": "eastmoney",
      "event_id": "em_jjsj_20251217180000_-7426517482757231003",
      "original_id": "2025-12-17 18:00:00_欧元区：CPI(报告期:2025年11月)",
      "event_date": "2025-12-17",
      "event_time": "18:00:00",
      "event_datetime": "2025-12-17 18:00:00",
      "title": "欧元区：CPI(报告期:2025年11月)",
      "content": null,
      "category": "经济数据",
      "importance": 4,
      "country": "欧盟",
      "city": null,
      "stocks": [],
      "concepts": [],
      "themes": [],
      "data_status": "ACTIVE",
      "is_new": true,
      "discovery_date": "2025-10-04",
      "raw_data": {
        "Name": "欧元区：CPI(报告期:2025年11月)",
        "City": "欧盟"
      },
      "created_at": "2025-10-04T00:45:14.976296"
    }
  ]
}