{
  "date": "2025-12-10",
  "total_events": 90,
  "new_events": 1,
  "platforms": {
    "cls": 3,
    "jiuyangongshe": 3,
    "tonghuashun": 3,
    "investing": 49,
    "eastmoney": 32
  },
  "events": [
    {
      "platform": "cls",
      "event_id": "cls_371638_20251210_2",
      "original_id": "371638",
      "event_date": "2025-12-10",
      "event_time": "00:00:00",
      "event_datetime": "2025-12-10 00:00:00",
      "title": "2025中国铂族金属市场年会定于12月10日在三亚召开",
      "content": null,
      "category": "事件公告",
      "importance": 5,
      "country": "中国",
      "city": null,
      "stocks": [],
      "concepts": [],
      "themes": [],
      "data_status": "ACTIVE",
      "is_new": false,
      "discovery_date": "2025-12-09",
      "raw_data": {
        "id": 371638,
        "calendar_time": "2025-12-10 00:00:00",
        "data_id": 20126,
        "type": 2,
        "economic": null,
        "event": {
          "title": "2025中国铂族金属市场年会定于12月10日在三亚召开",
          "country": "中国",
          "country_icon": "",
          "star": 5
        },
        "holiday": null,
        "title": "2025中国铂族金属市场年会定于12月10日在三亚召开"
      },
      "created_at": "2025-12-09T00:54:30.559969"
    },
    {
      "platform": "cls",
      "event_id": "cls_398750_20251210_2",
      "original_id": "398750",
      "event_date": "2025-12-10",
      "event_time": "00:00:00",
      "event_datetime": "2025-12-10 00:00:00",
      "title": "第二十届中国IDC产业年度大典将于12月10日至11日举办",
      "content": null,
      "category": "事件公告",
      "importance": 5,
      "country": "中国",
      "city": null,
      "stocks": [],
      "concepts": [],
      "themes": [],
      "data_status": "ACTIVE",
      "is_new": false,
      "discovery_date": "2025-12-09",
      "raw_data": {
        "id": 398750,
        "calendar_time": "2025-12-10 00:00:00",
        "data_id": 20335,
        "type": 2,
        "economic": null,
        "event": {
          "title": "第二十届中国IDC产业年度大典将于12月10日至11日举办",
          "country": "中国",
          "country_icon": "",
          "star": 5
        },
        "holiday": null,
        "title": "第二十届中国IDC产业年度大典将于12月10日至11日举办"
      },
      "created_at": "2025-12-09T00:54:30.559980"
    },
    {
      "platform": "cls",
      "event_id": "cls_366026_20251210_2",
      "original_id": "366026",
      "event_date": "2025-12-10",
      "event_time": "09:00:00",
      "event_datetime": "2025-12-10 09:00:00",
      "title": "EIA公布月度短期能源展望报告",
      "content": null,
      "category": "事件公告",
      "importance": 3,
      "country": "美国",
      "city": null,
      "stocks": [],
      "concepts": [],
      "themes": [],
      "data_status": "ACTIVE",
      "is_new": false,
      "discovery_date": "2025-12-09",
      "raw_data": {
        "id": 366026,
        "calendar_time": "2025-12-10 09:00:00",
        "data_id": 20077,
        "type": 2,
        "economic": null,
        "event": {
          "title": "EIA公布月度短期能源展望报告",
          "country": "美国",
          "country_icon": "",
          "star": 3
        },
        "holiday": null,
        "title": "EIA公布月度短期能源展望报告"
      },
      "created_at": "2025-12-09T00:54:30.559991"
    },
    {
      "platform": "jiuyangongshe",
      "event_id": "jygs_a7ee8c01bd3f497fa7d423bb2afc4c6a_438e3cbf6fbf4d628da354bd7cdb69fe_20251210",
      "original_id": "a7ee8c01bd3f497fa7d423bb2afc4c6a",
      "event_date": "2025-12-10",
      "event_time": null,
      "event_datetime": null,
      "title": "上海闵行将启幕首个脑机接口未来产业集聚区",
      "content": "",
      "category": null,
      "importance": 1,
      "country": "中国",
      "city": null,
      "stocks": [],
      "concepts": [],
      "themes": [
        "脑机接口"
      ],
      "data_status": "ACTIVE",
      "is_new": false,
      "discovery_date": "2025-12-09",
      "raw_data": {
        "article_id": "a7ee8c01bd3f497fa7d423bb2afc4c6a",
        "user_id": "1",
        "title": "上海闵行将启幕首个脑机接口未来产业集聚区",
        "content": "",
        "like_count": 2,
        "comment_count": 1,
        "forward_count": 0,
        "is_like": 0,
        "is_step": 0,
        "user": {
          "user_id": "1",
          "nickname": "韭菜团子"
        },
        "timeline": {
          "article_id": "a7ee8c01bd3f497fa7d423bb2afc4c6a",
          "timeline_id": "438e3cbf6fbf4d628da354bd7cdb69fe",
          "date": "2025-12-10",
          "grade": 6,
          "source": "2",
          "create_time": "2025-11-06 21:21:22",
          "theme_list": [
            {
              "timeline_theme_id": "1206f8611b76449ba609ffde40f64a9c",
              "name": "脑机接口"
            }
          ]
        }
      },
      "created_at": "2025-12-09T00:54:32.511045"
    },
    {
      "platform": "jiuyangongshe",
      "event_id": "jygs_0f2a11934d994390bdea2c1e4984ad65_0970f1bb98174e8ea8416f6acf25b6c5_20251210",
      "original_id": "0f2a11934d994390bdea2c1e4984ad65",
      "event_date": "2025-12-10",
      "event_time": null,
      "event_datetime": null,
      "title": "2025中国铂族金属市场年会",
      "content": "",
      "category": null,
      "importance": 1,
      "country": "中国",
      "city": null,
      "stocks": [],
      "concepts": [],
      "themes": [],
      "data_status": "ACTIVE",
      "is_new": false,
      "discovery_date": "2025-12-09",
      "raw_data": {
        "article_id": "0f2a11934d994390bdea2c1e4984ad65",
        "user_id": "1",
        "title": "2025中国铂族金属市场年会",
        "content": "",
        "like_count": 0,
        "comment_count": 0,
        "forward_count": 0,
        "is_like": 0,
        "is_step": 0,
        "user": {
          "user_id": "1",
          "nickname": "韭菜团子"
        },
        "timeline": {
          "article_id": "0f2a11934d994390bdea2c1e4984ad65",
          "timeline_id": "0970f1bb98174e8ea8416f6acf25b6c5",
          "date": "2025-12-10",
          "grade": 6,
          "source": "2",
          "create_time": "2025-11-12 22:18:49",
          "theme_list": []
        }
      },
      "created_at": "2025-12-09T00:54:32.511055"
    },
    {
      "platform": "jiuyangongshe",
      "event_id": "jygs_8bb3e583873f4c1d9ba88c6eaafa8281_ecde1524f9044a7486d8ec3f773fcd2d_20251210",
      "original_id": "8bb3e583873f4c1d9ba88c6eaafa8281",
      "event_date": "2025-12-10",
      "event_time": null,
      "event_datetime": null,
      "title": "ESMO(欧洲肿瘤内科学会)",
      "content": "",
      "category": null,
      "importance": 1,
      "country": "中国",
      "city": null,
      "stocks": [],
      "concepts": [],
      "themes": [],
      "data_status": "ACTIVE",
      "is_new": false,
      "discovery_date": "2025-12-09",
      "raw_data": {
        "article_id": "8bb3e583873f4c1d9ba88c6eaafa8281",
        "user_id": "1",
        "title": "ESMO(欧洲肿瘤内科学会)",
        "content": "",
        "like_count": 0,
        "comment_count": 0,
        "forward_count": 0,
        "is_like": 0,
        "is_step": 0,
        "user": {
          "user_id": "1",
          "nickname": "韭菜团子"
        },
        "timeline": {
          "article_id": "8bb3e583873f4c1d9ba88c6eaafa8281",
          "timeline_id": "ecde1524f9044a7486d8ec3f773fcd2d",
          "date": "2025-12-10",
          "grade": 6,
          "source": "2",
          "create_time": "2025-11-18 22:27:40",
          "theme_list": []
        }
      },
      "created_at": "2025-12-09T00:54:32.511065"
    },
    {
      "platform": "tonghuashun",
      "event_id": "ths_20251210_0_5ae19c4d",
      "original_id": "2025-12-10_0",
      "event_date": "2025-12-10",
      "event_time": null,
      "event_datetime": null,
      "title": "第二十届中国IDC产业年度大典将于12月10日至11日举办",
      "content": null,
      "category": null,
      "importance": 3,
      "country": "中国",
      "city": null,
      "stocks": [],
      "concepts": [],
      "themes": [],
      "data_status": "ACTIVE",
      "is_new": false,
      "discovery_date": "2025-12-09",
      "raw_data": {
        "event": [
          "第二十届中国IDC产业年度大典将于12月10日至11日举办",
          "",
          "",
          ""
        ],
        "concept": []
      },
      "created_at": "2025-12-09T00:54:34.255689"
    },
    {
      "platform": "tonghuashun",
      "event_id": "ths_20251210_1_5ae19c4d",
      "original_id": "2025-12-10_1",
      "event_date": "2025-12-10",
      "event_time": null,
      "event_datetime": null,
      "title": "第二十届中国IDC产业年度大典将于12月10日至11日举办",
      "content": null,
      "category": null,
      "importance": 3,
      "country": "中国",
      "city": null,
      "stocks": [],
      "concepts": [],
      "themes": [],
      "data_status": "ACTIVE",
      "is_new": false,
      "discovery_date": "2025-12-09",
      "raw_data": {
        "event": [
          "第二十届中国IDC产业年度大典将于12月10日至11日举办",
          "",
          "",
          ""
        ],
        "concept": []
      },
      "created_at": "2025-12-09T00:54:34.255698"
    },
    {
      "platform": "tonghuashun",
      "event_id": "ths_20251210_2_0326fa1f",
      "original_id": "2025-12-10_2",
      "event_date": "2025-12-10",
      "event_time": null,
      "event_datetime": null,
      "title": "2025中国铂族金属市场年会定于12月10日在三亚召开",
      "content": null,
      "category": null,
      "importance": 3,
      "country": "中国",
      "city": null,
      "stocks": [],
      "concepts": [],
      "themes": [],
      "data_status": "ACTIVE",
      "is_new": false,
      "discovery_date": "2025-12-09",
      "raw_data": {
        "event": [
          "2025中国铂族金属市场年会定于12月10日在三亚召开",
          "",
          "",
          ""
        ],
        "concept": []
      },
      "created_at": "2025-12-09T00:54:34.255707"
    },
    {
      "platform": "investing",
      "event_id": "inv__20251210010000",
      "original_id": "eventRowId_537593",
      "event_date": "2025-12-10",
      "event_time": "01:00",
      "event_datetime": "2025/12/10 01:00:00",
      "title": "美国EIA短期能源展望报告",
      "content": null,
      "category": null,
      "importance": 2,
      "country": "美国",
      "city": null,
      "stocks": [],
      "concepts": [],
      "themes": [],
      "data_status": "ACTIVE",
      "is_new": false,
      "discovery_date": "2025-12-09",
      "raw_data": {
        "event_id": "eventRowId_537593",
        "event_attr_id": "",
        "datetime": "2025/12/10 01:00:00",
        "time": "01:00",
        "country": "美国",
        "importance": 2,
        "event_name": "美国EIA短期能源展望报告"
      },
      "created_at": "2025-12-09T00:54:35.555262"
    },
    {
      "platform": "investing",
      "event_id": "inv__20251210010000",
      "original_id": "eventRowId_537418",
      "event_date": "2025-12-10",
      "event_time": "01:00",
      "event_datetime": "2025/12/10 01:00:00",
      "title": "美国农业部世界农产品供需预测报告",
      "content": null,
      "category": null,
      "importance": 2,
      "country": "美国",
      "city": null,
      "stocks": [],
      "concepts": [],
      "themes": [],
      "data_status": "ACTIVE",
      "is_new": false,
      "discovery_date": "2025-12-09",
      "raw_data": {
        "event_id": "eventRowId_537418",
        "event_attr_id": "",
        "datetime": "2025/12/10 01:00:00",
        "time": "01:00",
        "country": "美国",
        "importance": 2,
        "event_name": "美国农业部世界农产品供需预测报告"
      },
      "created_at": "2025-12-09T00:54:35.555415"
    },
    {
      "platform": "investing",
      "event_id": "inv__20251210020000",
      "original_id": "eventRowId_537419",
      "event_date": "2025-12-10",
      "event_time": "02:00",
      "event_datetime": "2025/12/10 02:00:00",
      "title": "美国10年期国债拍卖",
      "content": "前值: 4.074%",
      "category": null,
      "importance": 2,
      "country": "美国",
      "city": null,
      "stocks": [],
      "concepts": [],
      "themes": [],
      "data_status": "ACTIVE",
      "is_new": false,
      "discovery_date": "2025-12-09",
      "raw_data": {
        "event_id": "eventRowId_537419",
        "event_attr_id": "",
        "datetime": "2025/12/10 02:00:00",
        "time": "02:00",
        "country": "美国",
        "importance": 2,
        "event_name": "美国10年期国债拍卖",
        "previous": "4.074%"
      },
      "created_at": "2025-12-09T00:54:35.555547"
    },
    {
      "platform": "investing",
      "event_id": "inv__20251210053000",
      "original_id": "eventRowId_537420",
      "event_date": "2025-12-10",
      "event_time": "05:30",
      "event_datetime": "2025/12/10 05:30:00",
      "title": "美国当周API原油库存变动(桶)",
      "content": "前值: -2.480M",
      "category": null,
      "importance": 2,
      "country": "美国",
      "city": null,
      "stocks": [],
      "concepts": [],
      "themes": [],
      "data_status": "ACTIVE",
      "is_new": false,
      "discovery_date": "2025-12-09",
      "raw_data": {
        "event_id": "eventRowId_537420",
        "event_attr_id": "",
        "datetime": "2025/12/10 05:30:00",
        "time": "05:30",
        "country": "美国",
        "importance": 2,
        "event_name": "美国当周API原油库存变动(桶)",
        "previous": "-2.480M"
      },
      "created_at": "2025-12-09T00:54:35.555680"
    },
    {
      "platform": "investing",
      "event_id": "inv__20251210054500",
      "original_id": "eventRowId_536218",
      "event_date": "2025-12-10",
      "event_time": "05:45",
      "event_datetime": "2025/12/10 05:45:00",
      "title": "新西兰外部移民和游客年率(%)  (十月)",
      "content": "前值: 9.60%",
      "category": null,
      "importance": 1,
      "country": "新西兰",
      "city": null,
      "stocks": [],
      "concepts": [],
      "themes": [],
      "data_status": "ACTIVE",
      "is_new": false,
      "discovery_date": "2025-12-09",
      "raw_data": {
        "event_id": "eventRowId_536218",
        "event_attr_id": "",
        "datetime": "2025/12/10 05:45:00",
        "time": "05:45",
        "country": "新西兰",
        "importance": 1,
        "event_name": "新西兰外部移民和游客年率(%)  (十月)",
        "previous": "9.60%"
      },
      "created_at": "2025-12-09T00:54:35.555802"
    },
    {
      "platform": "investing",
      "event_id": "inv__20251210054500",
      "original_id": "eventRowId_536217",
      "event_date": "2025-12-10",
      "event_time": "05:45",
      "event_datetime": "2025/12/10 05:45:00",
      "title": "新西兰净流入移民人数(人)  (十月)",
      "content": "前值: 1,800",
      "category": null,
      "importance": 1,
      "country": "新西兰",
      "city": null,
      "stocks": [],
      "concepts": [],
      "themes": [],
      "data_status": "ACTIVE",
      "is_new": false,
      "discovery_date": "2025-12-09",
      "raw_data": {
        "event_id": "eventRowId_536217",
        "event_attr_id": "",
        "datetime": "2025/12/10 05:45:00",
        "time": "05:45",
        "country": "新西兰",
        "importance": 1,
        "event_name": "新西兰净流入移民人数(人)  (十月)",
        "previous": "1,800"
      },
      "created_at": "2025-12-09T00:54:35.555921"
    },
    {
      "platform": "investing",
      "event_id": "inv__20251210054500",
      "original_id": "eventRowId_537587",
      "event_date": "2025-12-10",
      "event_time": "05:45",
      "event_datetime": "2025/12/10 05:45:00",
      "title": "新西兰短期访客人数月率(%) (月度环比)",
      "content": "前值: 2.9%",
      "category": null,
      "importance": 1,
      "country": "新西兰",
      "city": null,
      "stocks": [],
      "concepts": [],
      "themes": [],
      "data_status": "ACTIVE",
      "is_new": false,
      "discovery_date": "2025-12-09",
      "raw_data": {
        "event_id": "eventRowId_537587",
        "event_attr_id": "",
        "datetime": "2025/12/10 05:45:00",
        "time": "05:45",
        "country": "新西兰",
        "importance": 1,
        "event_name": "新西兰短期访客人数月率(%) (月度环比)",
        "previous": "2.9%"
      },
      "created_at": "2025-12-09T00:54:35.556037"
    },
    {
      "platform": "investing",
      "event_id": "inv__20251210070000",
      "original_id": "eventRowId_536219",
      "event_date": "2025-12-10",
      "event_time": "07:00",
      "event_datetime": "2025/12/10 07:00:00",
      "title": "韩国失业率  (十一月)",
      "content": "前值: 2.6%",
      "category": null,
      "importance": 1,
      "country": "韩国",
      "city": null,
      "stocks": [],
      "concepts": [],
      "themes": [],
      "data_status": "ACTIVE",
      "is_new": false,
      "discovery_date": "2025-12-09",
      "raw_data": {
        "event_id": "eventRowId_536219",
        "event_attr_id": "",
        "datetime": "2025/12/10 07:00:00",
        "time": "07:00",
        "country": "韩国",
        "importance": 1,
        "event_name": "韩国失业率  (十一月)",
        "previous": "2.6%"
      },
      "created_at": "2025-12-09T00:54:35.556192"
    },
    {
      "platform": "investing",
      "event_id": "inv__20251210070000",
      "original_id": "eventRowId_536917",
      "event_date": "2025-12-10",
      "event_time": "07:00",
      "event_datetime": "2025/12/10 07:00:00",
      "title": "日本路透短观指数  (十二月)",
      "content": "前值: 17",
      "category": null,
      "importance": 1,
      "country": "日本",
      "city": null,
      "stocks": [],
      "concepts": [],
      "themes": [],
      "data_status": "ACTIVE",
      "is_new": false,
      "discovery_date": "2025-12-09",
      "raw_data": {
        "event_id": "eventRowId_536917",
        "event_attr_id": "",
        "datetime": "2025/12/10 07:00:00",
        "time": "07:00",
        "country": "日本",
        "importance": 1,
        "event_name": "日本路透短观指数  (十二月)",
        "previous": "17"
      },
      "created_at": "2025-12-09T00:54:35.556330"
    },
    {
      "platform": "investing",
      "event_id": "inv__20251210075000",
      "original_id": "eventRowId_536222",
      "event_date": "2025-12-10",
      "event_time": "07:50",
      "event_datetime": "2025/12/10 07:50:00",
      "title": "日本国内企业商品物价指数年率(%) (同比)  (十一月)",
      "content": "预测值: 2.7% | 前值: 2.7%",
      "category": null,
      "importance": 1,
      "country": "日本",
      "city": null,
      "stocks": [],
      "concepts": [],
      "themes": [],
      "data_status": "ACTIVE",
      "is_new": false,
      "discovery_date": "2025-12-09",
      "raw_data": {
        "event_id": "eventRowId_536222",
        "event_attr_id": "",
        "datetime": "2025/12/10 07:50:00",
        "time": "07:50",
        "country": "日本",
        "importance": 1,
        "event_name": "日本国内企业商品物价指数年率(%) (同比)  (十一月)",
        "forecast": "2.7%",
        "previous": "2.7%"
      },
      "created_at": "2025-12-09T00:54:35.556457"
    },
    {
      "platform": "investing",
      "event_id": "inv__20251210075000",
      "original_id": "eventRowId_536221",
      "event_date": "2025-12-10",
      "event_time": "07:50",
      "event_datetime": "2025/12/10 07:50:00",
      "title": "日本PPI月率 (月度环比)  (十一月)",
      "content": "预测值: 0.3% | 前值: 0.4%",
      "category": null,
      "importance": 1,
      "country": "日本",
      "city": null,
      "stocks": [],
      "concepts": [],
      "themes": [],
      "data_status": "ACTIVE",
      "is_new": false,
      "discovery_date": "2025-12-09",
      "raw_data": {
        "event_id": "eventRowId_536221",
        "event_attr_id": "",
        "datetime": "2025/12/10 07:50:00",
        "time": "07:50",
        "country": "日本",
        "importance": 1,
        "event_name": "日本PPI月率 (月度环比)  (十一月)",
        "forecast": "0.3%",
        "previous": "0.4%"
      },
      "created_at": "2025-12-09T00:54:35.556582"
    },
    {
      "platform": "investing",
      "event_id": "inv__20251210083000",
      "original_id": "eventRowId_537422",
      "event_date": "2025-12-10",
      "event_time": "08:30",
      "event_datetime": "2025/12/10 08:30:00",
      "title": "澳洲央行经济和金融市场图表集",
      "content": null,
      "category": null,
      "importance": 1,
      "country": "澳大利亚",
      "city": null,
      "stocks": [],
      "concepts": [],
      "themes": [],
      "data_status": "ACTIVE",
      "is_new": false,
      "discovery_date": "2025-12-09",
      "raw_data": {
        "event_id": "eventRowId_537422",
        "event_attr_id": "",
        "datetime": "2025/12/10 08:30:00",
        "time": "08:30",
        "country": "澳大利亚",
        "importance": 1,
        "event_name": "澳洲央行经济和金融市场图表集"
      },
      "created_at": "2025-12-09T00:54:35.556701"
    },
    {
      "platform": "investing",
      "event_id": "inv__20251210093000",
      "original_id": "eventRowId_536226",
      "event_date": "2025-12-10",
      "event_time": "09:30",
      "event_datetime": "2025/12/10 09:30:00",
      "title": "中国CPI年率(%) (同比)  (十一月)",
      "content": "预测值: 0.7% | 前值: 0.2%",
      "category": null,
      "importance": 3,
      "country": "中国",
      "city": null,
      "stocks": [],
      "concepts": [],
      "themes": [],
      "data_status": "ACTIVE",
      "is_new": false,
      "discovery_date": "2025-12-09",
      "raw_data": {
        "event_id": "eventRowId_536226",
        "event_attr_id": "",
        "datetime": "2025/12/10 09:30:00",
        "time": "09:30",
        "country": "中国",
        "importance": 3,
        "event_name": "中国CPI年率(%) (同比)  (十一月)",
        "forecast": "0.7%",
        "previous": "0.2%"
      },
      "created_at": "2025-12-09T00:54:35.556847"
    },
    {
      "platform": "investing",
      "event_id": "inv__20251210093000",
      "original_id": "eventRowId_536225",
      "event_date": "2025-12-10",
      "event_time": "09:30",
      "event_datetime": "2025/12/10 09:30:00",
      "title": "中国CPI月率(%) (月度环比)  (十一月)",
      "content": "预测值: 0.3% | 前值: 0.2%",
      "category": null,
      "importance": 3,
      "country": "中国",
      "city": null,
      "stocks": [],
      "concepts": [],
      "themes": [],
      "data_status": "ACTIVE",
      "is_new": false,
      "discovery_date": "2025-12-09",
      "raw_data": {
        "event_id": "eventRowId_536225",
        "event_attr_id": "",
        "datetime": "2025/12/10 09:30:00",
        "time": "09:30",
        "country": "中国",
        "importance": 3,
        "event_name": "中国CPI月率(%) (月度环比)  (十一月)",
        "forecast": "0.3%",
        "previous": "0.2%"
      },
      "created_at": "2025-12-09T00:54:35.556978"
    },
    {
      "platform": "investing",
      "event_id": "inv__20251210093000",
      "original_id": "eventRowId_536227",
      "event_date": "2025-12-10",
      "event_time": "09:30",
      "event_datetime": "2025/12/10 09:30:00",
      "title": "中国PPI年率(%) (同比)  (十一月)",
      "content": "预测值: -2.1% | 前值: -2.1%",
      "category": null,
      "importance": 3,
      "country": "中国",
      "city": null,
      "stocks": [],
      "concepts": [],
      "themes": [],
      "data_status": "ACTIVE",
      "is_new": false,
      "discovery_date": "2025-12-09",
      "raw_data": {
        "event_id": "eventRowId_536227",
        "event_attr_id": "",
        "datetime": "2025/12/10 09:30:00",
        "time": "09:30",
        "country": "中国",
        "importance": 3,
        "event_name": "中国PPI年率(%) (同比)  (十一月)",
        "forecast": "-2.1%",
        "previous": "-2.1%"
      },
      "created_at": "2025-12-09T00:54:35.557097"
    },
    {
      "platform": "investing",
      "event_id": "inv__20251210120000",
      "original_id": "eventRowId_537423",
      "event_date": "2025-12-10",
      "event_time": "12:00",
      "event_datetime": "2025/12/10 12:00:00",
      "title": "马来西亚失业率  (十月)",
      "content": "前值: 3.0%",
      "category": null,
      "importance": 1,
      "country": "马来西亚",
      "city": null,
      "stocks": [],
      "concepts": [],
      "themes": [],
      "data_status": "ACTIVE",
      "is_new": false,
      "discovery_date": "2025-12-09",
      "raw_data": {
        "event_id": "eventRowId_537423",
        "event_attr_id": "",
        "datetime": "2025/12/10 12:00:00",
        "time": "12:00",
        "country": "马来西亚",
        "importance": 1,
        "event_name": "马来西亚失业率  (十月)",
        "previous": "3.0%"
      },
      "created_at": "2025-12-09T00:54:35.557234"
    },
    {
      "platform": "investing",
      "event_id": "inv__20251210120000",
      "original_id": "eventRowId_536228",
      "event_date": "2025-12-10",
      "event_time": "12:00",
      "event_datetime": "2025/12/10 12:00:00",
      "title": "印度尼西亚零售销售年率(%) (同比)  (十月)",
      "content": "前值: 3.7%",
      "category": null,
      "importance": 1,
      "country": "印度尼西亚",
      "city": null,
      "stocks": [],
      "concepts": [],
      "themes": [],
      "data_status": "ACTIVE",
      "is_new": false,
      "discovery_date": "2025-12-09",
      "raw_data": {
        "event_id": "eventRowId_536228",
        "event_attr_id": "",
        "datetime": "2025/12/10 12:00:00",
        "time": "12:00",
        "country": "印度尼西亚",
        "importance": 1,
        "event_name": "印度尼西亚零售销售年率(%) (同比)  (十月)",
        "previous": "3.7%"
      },
      "created_at": "2025-12-09T00:54:35.557354"
    },
    {
      "platform": "investing",
      "event_id": "inv__20251210170000",
      "original_id": "eventRowId_536355",
      "event_date": "2025-12-10",
      "event_time": "17:00",
      "event_datetime": "2025/12/10 17:00:00",
      "title": "意大利季调后工业产出月率(%) (月度环比)  (十月)",
      "content": "预测值: -0.3% | 前值: 2.8%",
      "category": null,
      "importance": 1,
      "country": "意大利",
      "city": null,
      "stocks": [],
      "concepts": [],
      "themes": [],
      "data_status": "ACTIVE",
      "is_new": false,
      "discovery_date": "2025-12-09",
      "raw_data": {
        "event_id": "eventRowId_536355",
        "event_attr_id": "",
        "datetime": "2025/12/10 17:00:00",
        "time": "17:00",
        "country": "意大利",
        "importance": 1,
        "event_name": "意大利季调后工业产出月率(%) (月度环比)  (十月)",
        "forecast": "-0.3%",
        "previous": "2.8%"
      },
      "created_at": "2025-12-09T00:54:35.557477"
    },
    {
      "platform": "investing",
      "event_id": "inv__20251210170000",
      "original_id": "eventRowId_536354",
      "event_date": "2025-12-10",
      "event_time": "17:00",
      "event_datetime": "2025/12/10 17:00:00",
      "title": "意大利未季调工业产出年率(%) (同比)  (十月)",
      "content": "前值: 1.5%",
      "category": null,
      "importance": 1,
      "country": "意大利",
      "city": null,
      "stocks": [],
      "concepts": [],
      "themes": [],
      "data_status": "ACTIVE",
      "is_new": false,
      "discovery_date": "2025-12-09",
      "raw_data": {
        "event_id": "eventRowId_536354",
        "event_attr_id": "",
        "datetime": "2025/12/10 17:00:00",
        "time": "17:00",
        "country": "意大利",
        "importance": 1,
        "event_name": "意大利未季调工业产出年率(%) (同比)  (十月)",
        "previous": "1.5%"
      },
      "created_at": "2025-12-09T00:54:35.557595"
    },
    {
      "platform": "investing",
      "event_id": "inv__20251210181000",
      "original_id": "eventRowId_537427",
      "event_date": "2025-12-10",
      "event_time": "18:10",
      "event_datetime": "2025/12/10 18:10:00",
      "title": "意大利12个月期BOT国债拍卖平均收益率(%)",
      "content": "前值: 2.063%",
      "category": null,
      "importance": 1,
      "country": "意大利",
      "city": null,
      "stocks": [],
      "concepts": [],
      "themes": [],
      "data_status": "ACTIVE",
      "is_new": false,
      "discovery_date": "2025-12-09",
      "raw_data": {
        "event_id": "eventRowId_537427",
        "event_attr_id": "",
        "datetime": "2025/12/10 18:10:00",
        "time": "18:10",
        "country": "意大利",
        "importance": 1,
        "event_name": "意大利12个月期BOT国债拍卖平均收益率(%)",
        "previous": "2.063%"
      },
      "created_at": "2025-12-09T00:54:35.557711"
    },
    {
      "platform": "investing",
      "event_id": "inv__20251210184500",
      "original_id": "eventRowId_537649",
      "event_date": "2025-12-10",
      "event_time": "18:45",
      "event_datetime": "2025/12/10 18:45:00",
      "title": "英国央行行长贝利(Andrew Bailey)讲话",
      "content": null,
      "category": null,
      "importance": 2,
      "country": "英国",
      "city": null,
      "stocks": [],
      "concepts": [],
      "themes": [],
      "data_status": "ACTIVE",
      "is_new": false,
      "discovery_date": "2025-12-09",
      "raw_data": {
        "event_id": "eventRowId_537649",
        "event_attr_id": "",
        "datetime": "2025/12/10 18:45:00",
        "time": "18:45",
        "country": "英国",
        "importance": 2,
        "event_name": "英国央行行长贝利(Andrew Bailey)讲话"
      },
      "created_at": "2025-12-09T00:54:35.557824"
    },
    {
      "platform": "investing",
      "event_id": "inv__20251210185500",
      "original_id": "eventRowId_537588",
      "event_date": "2025-12-10",
      "event_time": "18:55",
      "event_datetime": "2025/12/10 18:55:00",
      "title": "欧洲央行行长拉加德(Christine Lagarde)讲话",
      "content": null,
      "category": null,
      "importance": 2,
      "country": "欧元区",
      "city": null,
      "stocks": [],
      "concepts": [],
      "themes": [],
      "data_status": "ACTIVE",
      "is_new": false,
      "discovery_date": "2025-12-09",
      "raw_data": {
        "event_id": "eventRowId_537588",
        "event_attr_id": "",
        "datetime": "2025/12/10 18:55:00",
        "time": "18:55",
        "country": "欧元区",
        "importance": 2,
        "event_name": "欧洲央行行长拉加德(Christine Lagarde)讲话"
      },
      "created_at": "2025-12-09T00:54:35.557940"
    },
    {
      "platform": "investing",
      "event_id": "inv__20251210190000",
      "original_id": "eventRowId_536473",
      "event_date": "2025-12-10",
      "event_time": "19:00",
      "event_datetime": "2025/12/10 19:00:00",
      "title": "南非零售销售年率(%) (同比)  (十月)",
      "content": "前值: 3.1%",
      "category": null,
      "importance": 1,
      "country": "南非",
      "city": null,
      "stocks": [],
      "concepts": [],
      "themes": [],
      "data_status": "ACTIVE",
      "is_new": false,
      "discovery_date": "2025-12-09",
      "raw_data": {
        "event_id": "eventRowId_536473",
        "event_attr_id": "",
        "datetime": "2025/12/10 19:00:00",
        "time": "19:00",
        "country": "南非",
        "importance": 1,
        "event_name": "南非零售销售年率(%) (同比)  (十月)",
        "previous": "3.1%"
      },
      "created_at": "2025-12-09T00:54:35.558065"
    },
    {
      "platform": "investing",
      "event_id": "inv__20251210193000",
      "original_id": "eventRowId_537428",
      "event_date": "2025-12-10",
      "event_time": "19:30",
      "event_datetime": "2025/12/10 19:30:00",
      "title": "印度M3货币供应量(%)",
      "content": "前值: 9.8%",
      "category": null,
      "importance": 1,
      "country": "印度",
      "city": null,
      "stocks": [],
      "concepts": [],
      "themes": [],
      "data_status": "ACTIVE",
      "is_new": false,
      "discovery_date": "2025-12-09",
      "raw_data": {
        "event_id": "eventRowId_537428",
        "event_attr_id": "",
        "datetime": "2025/12/10 19:30:00",
        "time": "19:30",
        "country": "印度",
        "importance": 1,
        "event_name": "印度M3货币供应量(%)",
        "previous": "9.8%"
      },
      "created_at": "2025-12-09T00:54:35.558200"
    },
    {
      "platform": "investing",
      "event_id": "inv__20251210200000",
      "original_id": "eventRowId_537499",
      "event_date": "2025-12-10",
      "event_time": "20:00",
      "event_datetime": "2025/12/10 20:00:00",
      "title": "美国MBA30年期固定抵押贷款利率(%)",
      "content": "前值: 6.32%",
      "category": null,
      "importance": 1,
      "country": "美国",
      "city": null,
      "stocks": [],
      "concepts": [],
      "themes": [],
      "data_status": "ACTIVE",
      "is_new": false,
      "discovery_date": "2025-12-09",
      "raw_data": {
        "event_id": "eventRowId_537499",
        "event_attr_id": "",
        "datetime": "2025/12/10 20:00:00",
        "time": "20:00",
        "country": "美国",
        "importance": 1,
        "event_name": "美国MBA30年期固定抵押贷款利率(%)",
        "previous": "6.32%"
      },
      "created_at": "2025-12-09T00:54:35.558325"
    },
    {
      "platform": "investing",
      "event_id": "inv__20251210200000",
      "original_id": "eventRowId_537500",
      "event_date": "2025-12-10",
      "event_time": "20:00",
      "event_datetime": "2025/12/10 20:00:00",
      "title": "美国MBA抵押贷款申请活动指数周环比(%) (每周)",
      "content": "前值: -1.4%",
      "category": null,
      "importance": 1,
      "country": "美国",
      "city": null,
      "stocks": [],
      "concepts": [],
      "themes": [],
      "data_status": "ACTIVE",
      "is_new": false,
      "discovery_date": "2025-12-09",
      "raw_data": {
        "event_id": "eventRowId_537500",
        "event_attr_id": "",
        "datetime": "2025/12/10 20:00:00",
        "time": "20:00",
        "country": "美国",
        "importance": 1,
        "event_name": "美国MBA抵押贷款申请活动指数周环比(%) (每周)",
        "previous": "-1.4%"
      },
      "created_at": "2025-12-09T00:54:35.558445"
    },
    {
      "platform": "investing",
      "event_id": "inv__20251210200000",
      "original_id": "eventRowId_537501",
      "event_date": "2025-12-10",
      "event_time": "20:00",
      "event_datetime": "2025/12/10 20:00:00",
      "title": "美国MBA抵押贷款购买指数",
      "content": "前值: 186.1",
      "category": null,
      "importance": 1,
      "country": "美国",
      "city": null,
      "stocks": [],
      "concepts": [],
      "themes": [],
      "data_status": "ACTIVE",
      "is_new": false,
      "discovery_date": "2025-12-09",
      "raw_data": {
        "event_id": "eventRowId_537501",
        "event_attr_id": "",
        "datetime": "2025/12/10 20:00:00",
        "time": "20:00",
        "country": "美国",
        "importance": 1,
        "event_name": "美国MBA抵押贷款购买指数",
        "previous": "186.1"
      },
      "created_at": "2025-12-09T00:54:35.558560"
    },
    {
      "platform": "investing",
      "event_id": "inv__20251210200000",
      "original_id": "eventRowId_537502",
      "event_date": "2025-12-10",
      "event_time": "20:00",
      "event_datetime": "2025/12/10 20:00:00",
      "title": "美国MBA抵押贷款申请活动指数",
      "content": "前值: 313.0",
      "category": null,
      "importance": 1,
      "country": "美国",
      "city": null,
      "stocks": [],
      "concepts": [],
      "themes": [],
      "data_status": "ACTIVE",
      "is_new": false,
      "discovery_date": "2025-12-09",
      "raw_data": {
        "event_id": "eventRowId_537502",
        "event_attr_id": "",
        "datetime": "2025/12/10 20:00:00",
        "time": "20:00",
        "country": "美国",
        "importance": 1,
        "event_name": "美国MBA抵押贷款申请活动指数",
        "previous": "313.0"
      },
      "created_at": "2025-12-09T00:54:35.558674"
    },
    {
      "platform": "investing",
      "event_id": "inv__20251210200000",
      "original_id": "eventRowId_537503",
      "event_date": "2025-12-10",
      "event_time": "20:00",
      "event_datetime": "2025/12/10 20:00:00",
      "title": "美国MBA抵押贷款再融资活动指数",
      "content": "前值: 1,041.9",
      "category": null,
      "importance": 1,
      "country": "美国",
      "city": null,
      "stocks": [],
      "concepts": [],
      "themes": [],
      "data_status": "ACTIVE",
      "is_new": false,
      "discovery_date": "2025-12-09",
      "raw_data": {
        "event_id": "eventRowId_537503",
        "event_attr_id": "",
        "datetime": "2025/12/10 20:00:00",
        "time": "20:00",
        "country": "美国",
        "importance": 1,
        "event_name": "美国MBA抵押贷款再融资活动指数",
        "previous": "1,041.9"
      },
      "created_at": "2025-12-09T00:54:35.558789"
    },
    {
      "platform": "investing",
      "event_id": "inv__20251210200000",
      "original_id": "eventRowId_536364",
      "event_date": "2025-12-10",
      "event_time": "20:00",
      "event_datetime": "2025/12/10 20:00:00",
      "title": "巴西CPI月率(%) (月度环比)  (十一月)",
      "content": "预测值: 0.09% | 前值: 0.09%",
      "category": null,
      "importance": 1,
      "country": "巴西",
      "city": null,
      "stocks": [],
      "concepts": [],
      "themes": [],
      "data_status": "ACTIVE",
      "is_new": false,
      "discovery_date": "2025-12-09",
      "raw_data": {
        "event_id": "eventRowId_536364",
        "event_attr_id": "",
        "datetime": "2025/12/10 20:00:00",
        "time": "20:00",
        "country": "巴西",
        "importance": 1,
        "event_name": "巴西CPI月率(%) (月度环比)  (十一月)",
        "forecast": "0.09%",
        "previous": "0.09%"
      },
      "created_at": "2025-12-09T00:54:35.558903"
    },
    {
      "platform": "investing",
      "event_id": "inv__20251210200000",
      "original_id": "eventRowId_536365",
      "event_date": "2025-12-10",
      "event_time": "20:00",
      "event_datetime": "2025/12/10 20:00:00",
      "title": "巴西CPI年率(%) (同比)  (十一月)",
      "content": "前值: 4.68%",
      "category": null,
      "importance": 2,
      "country": "巴西",
      "city": null,
      "stocks": [],
      "concepts": [],
      "themes": [],
      "data_status": "ACTIVE",
      "is_new": false,
      "discovery_date": "2025-12-09",
      "raw_data": {
        "event_id": "eventRowId_536365",
        "event_attr_id": "",
        "datetime": "2025/12/10 20:00:00",
        "time": "20:00",
        "country": "巴西",
        "importance": 2,
        "event_name": "巴西CPI年率(%) (同比)  (十一月)",
        "previous": "4.68%"
      },
      "created_at": "2025-12-09T00:54:35.559021"
    },
    {
      "platform": "investing",
      "event_id": "inv__20251210200000",
      "original_id": "eventRowId_536363",
      "event_date": "2025-12-10",
      "event_time": "20:00",
      "event_datetime": "2025/12/10 20:00:00",
      "title": "巴西季调后IPCA通胀指数月率 (月度环比)  (十一月)",
      "content": "前值: 0.07%",
      "category": null,
      "importance": 1,
      "country": "巴西",
      "city": null,
      "stocks": [],
      "concepts": [],
      "themes": [],
      "data_status": "ACTIVE",
      "is_new": false,
      "discovery_date": "2025-12-09",
      "raw_data": {
        "event_id": "eventRowId_536363",
        "event_attr_id": "",
        "datetime": "2025/12/10 20:00:00",
        "time": "20:00",
        "country": "巴西",
        "importance": 1,
        "event_name": "巴西季调后IPCA通胀指数月率 (月度环比)  (十一月)",
        "previous": "0.07%"
      },
      "created_at": "2025-12-09T00:54:35.559138"
    },
    {
      "platform": "investing",
      "event_id": "inv__20251210213000",
      "original_id": "eventRowId_536760",
      "event_date": "2025-12-10",
      "event_time": "21:30",
      "event_datetime": "2025/12/10 21:30:00",
      "title": "美国就业福利季率(%) (季度环比)  (第三季度)",
      "content": "前值: 0.70%",
      "category": null,
      "importance": 1,
      "country": "美国",
      "city": null,
      "stocks": [],
      "concepts": [],
      "themes": [],
      "data_status": "ACTIVE",
      "is_new": false,
      "discovery_date": "2025-12-09",
      "raw_data": {
        "event_id": "eventRowId_536760",
        "event_attr_id": "",
        "datetime": "2025/12/10 21:30:00",
        "time": "21:30",
        "country": "美国",
        "importance": 1,
        "event_name": "美国就业福利季率(%) (季度环比)  (第三季度)",
        "previous": "0.70%"
      },
      "created_at": "2025-12-09T00:54:35.559274"
    },
    {
      "platform": "investing",
      "event_id": "inv__20251210213000",
      "original_id": "eventRowId_536758",
      "event_date": "2025-12-10",
      "event_time": "21:30",
      "event_datetime": "2025/12/10 21:30:00",
      "title": "美国劳工就业成本季率(%) (季度环比)  (第三季度)",
      "content": "预测值: 0.9% | 前值: 0.9%",
      "category": null,
      "importance": 2,
      "country": "美国",
      "city": null,
      "stocks": [],
      "concepts": [],
      "themes": [],
      "data_status": "ACTIVE",
      "is_new": false,
      "discovery_date": "2025-12-09",
      "raw_data": {
        "event_id": "eventRowId_536758",
        "event_attr_id": "",
        "datetime": "2025/12/10 21:30:00",
        "time": "21:30",
        "country": "美国",
        "importance": 2,
        "event_name": "美国劳工就业成本季率(%) (季度环比)  (第三季度)",
        "forecast": "0.9%",
        "previous": "0.9%"
      },
      "created_at": "2025-12-09T00:54:35.559391"
    },
    {
      "platform": "investing",
      "event_id": "inv__20251210213000",
      "original_id": "eventRowId_536759",
      "event_date": "2025-12-10",
      "event_time": "21:30",
      "event_datetime": "2025/12/10 21:30:00",
      "title": "美国就业薪资季率(%) (季度环比)  (第三季度)",
      "content": "前值: 1.00%",
      "category": null,
      "importance": 1,
      "country": "美国",
      "city": null,
      "stocks": [],
      "concepts": [],
      "themes": [],
      "data_status": "ACTIVE",
      "is_new": false,
      "discovery_date": "2025-12-09",
      "raw_data": {
        "event_id": "eventRowId_536759",
        "event_attr_id": "",
        "datetime": "2025/12/10 21:30:00",
        "time": "21:30",
        "country": "美国",
        "importance": 1,
        "event_name": "美国就业薪资季率(%) (季度环比)  (第三季度)",
        "previous": "1.00%"
      },
      "created_at": "2025-12-09T00:54:35.559507"
    },
    {
      "platform": "investing",
      "event_id": "inv__20251210213000",
      "original_id": "eventRowId_536645",
      "event_date": "2025-12-10",
      "event_time": "21:30",
      "event_datetime": "2025/12/10 21:30:00",
      "title": "美国实际个人收入月率(%) (月度环比)  (十月)",
      "content": "前值: -0.1%",
      "category": null,
      "importance": 1,
      "country": "美国",
      "city": null,
      "stocks": [],
      "concepts": [],
      "themes": [],
      "data_status": "ACTIVE",
      "is_new": false,
      "discovery_date": "2025-12-09",
      "raw_data": {
        "event_id": "eventRowId_536645",
        "event_attr_id": "",
        "datetime": "2025/12/10 21:30:00",
        "time": "21:30",
        "country": "美国",
        "importance": 1,
        "event_name": "美国实际个人收入月率(%) (月度环比)  (十月)",
        "previous": "-0.1%"
      },
      "created_at": "2025-12-09T00:54:35.559625"
    },
    {
      "platform": "investing",
      "event_id": "inv__20251210224500",
      "original_id": "eventRowId_537505",
      "event_date": "2025-12-10",
      "event_time": "22:45",
      "event_datetime": "2025/12/10 22:45:00",
      "title": "加拿大央行利率决议",
      "content": null,
      "category": null,
      "importance": 2,
      "country": "加拿大",
      "city": null,
      "stocks": [],
      "concepts": [],
      "themes": [],
      "data_status": "ACTIVE",
      "is_new": false,
      "discovery_date": "2025-12-09",
      "raw_data": {
        "event_id": "eventRowId_537505",
        "event_attr_id": "",
        "datetime": "2025/12/10 22:45:00",
        "time": "22:45",
        "country": "加拿大",
        "importance": 2,
        "event_name": "加拿大央行利率决议"
      },
      "created_at": "2025-12-09T00:54:35.559739"
    },
    {
      "platform": "investing",
      "event_id": "inv__20251210224500",
      "original_id": "eventRowId_537023",
      "event_date": "2025-12-10",
      "event_time": "22:45",
      "event_datetime": "2025/12/10 22:45:00",
      "title": "加拿大央行利率决议",
      "content": "预测值: 2.25% | 前值: 2.25%",
      "category": null,
      "importance": 3,
      "country": "加拿大",
      "city": null,
      "stocks": [],
      "concepts": [],
      "themes": [],
      "data_status": "ACTIVE",
      "is_new": false,
      "discovery_date": "2025-12-09",
      "raw_data": {
        "event_id": "eventRowId_537023",
        "event_attr_id": "",
        "datetime": "2025/12/10 22:45:00",
        "time": "22:45",
        "country": "加拿大",
        "importance": 3,
        "event_name": "加拿大央行利率决议",
        "forecast": "2.25%",
        "previous": "2.25%"
      },
      "created_at": "2025-12-09T00:54:35.559856"
    },
    {
      "platform": "investing",
      "event_id": "inv__20251210233000",
      "original_id": "eventRowId_537543",
      "event_date": "2025-12-10",
      "event_time": "23:30",
      "event_datetime": "2025/12/10 23:30:00",
      "title": "美国当周EIA原油库存变动(桶)",
      "content": "前值: 0.574M",
      "category": null,
      "importance": 3,
      "country": "美国",
      "city": null,
      "stocks": [],
      "concepts": [],
      "themes": [],
      "data_status": "ACTIVE",
      "is_new": false,
      "discovery_date": "2025-12-09",
      "raw_data": {
        "event_id": "eventRowId_537543",
        "event_attr_id": "",
        "datetime": "2025/12/10 23:30:00",
        "time": "23:30",
        "country": "美国",
        "importance": 3,
        "event_name": "美国当周EIA原油库存变动(桶)",
        "previous": "0.574M"
      },
      "created_at": "2025-12-09T00:54:35.559971"
    },
    {
      "platform": "investing",
      "event_id": "inv__20251210233000",
      "original_id": "eventRowId_537542",
      "event_date": "2025-12-10",
      "event_time": "23:30",
      "event_datetime": "2025/12/10 23:30:00",
      "title": "美国当周EIA精炼厂原油消耗量变动 (每周)",
      "content": "前值: 0.433M",
      "category": null,
      "importance": 1,
      "country": "美国",
      "city": null,
      "stocks": [],
      "concepts": [],
      "themes": [],
      "data_status": "ACTIVE",
      "is_new": false,
      "discovery_date": "2025-12-09",
      "raw_data": {
        "event_id": "eventRowId_537542",
        "event_attr_id": "",
        "datetime": "2025/12/10 23:30:00",
        "time": "23:30",
        "country": "美国",
        "importance": 1,
        "event_name": "美国当周EIA精炼厂原油消耗量变动 (每周)",
        "previous": "0.433M"
      },
      "created_at": "2025-12-09T00:54:35.560085"
    },
    {
      "platform": "investing",
      "event_id": "inv__20251210233000",
      "original_id": "eventRowId_537546",
      "event_date": "2025-12-10",
      "event_time": "23:30",
      "event_datetime": "2025/12/10 23:30:00",
      "title": "美国当周EIA原油进口变动(桶)",
      "content": "前值: -0.470M",
      "category": null,
      "importance": 1,
      "country": "美国",
      "city": null,
      "stocks": [],
      "concepts": [],
      "themes": [],
      "data_status": "ACTIVE",
      "is_new": false,
      "discovery_date": "2025-12-09",
      "raw_data": {
        "event_id": "eventRowId_537546",
        "event_attr_id": "",
        "datetime": "2025/12/10 23:30:00",
        "time": "23:30",
        "country": "美国",
        "importance": 1,
        "event_name": "美国当周EIA原油进口变动(桶)",
        "previous": "-0.470M"
      },
      "created_at": "2025-12-09T00:54:35.560248"
    },
    {
      "platform": "investing",
      "event_id": "inv__20251210233000",
      "original_id": "eventRowId_537540",
      "event_date": "2025-12-10",
      "event_time": "23:30",
      "event_datetime": "2025/12/10 23:30:00",
      "title": "美国当周EIA库欣原油库存变动(桶)",
      "content": "前值: -0.457M",
      "category": null,
      "importance": 2,
      "country": "美国",
      "city": null,
      "stocks": [],
      "concepts": [],
      "themes": [],
      "data_status": "ACTIVE",
      "is_new": false,
      "discovery_date": "2025-12-09",
      "raw_data": {
        "event_id": "eventRowId_537540",
        "event_attr_id": "",
        "datetime": "2025/12/10 23:30:00",
        "time": "23:30",
        "country": "美国",
        "importance": 2,
        "event_name": "美国当周EIA库欣原油库存变动(桶)",
        "previous": "-0.457M"
      },
      "created_at": "2025-12-09T00:54:35.560373"
    },
    {
      "platform": "investing",
      "event_id": "inv__20251210233000",
      "original_id": "eventRowId_537545",
      "event_date": "2025-12-10",
      "event_time": "23:30",
      "event_datetime": "2025/12/10 23:30:00",
      "title": "美国当周EIA精炼油产量变动(桶)",
      "content": "前值: 0.053M",
      "category": null,
      "importance": 1,
      "country": "美国",
      "city": null,
      "stocks": [],
      "concepts": [],
      "themes": [],
      "data_status": "ACTIVE",
      "is_new": false,
      "discovery_date": "2025-12-09",
      "raw_data": {
        "event_id": "eventRowId_537545",
        "event_attr_id": "",
        "datetime": "2025/12/10 23:30:00",
        "time": "23:30",
        "country": "美国",
        "importance": 1,
        "event_name": "美国当周EIA精炼油产量变动(桶)",
        "previous": "0.053M"
      },
      "created_at": "2025-12-09T00:54:35.560489"
    },
    {
      "platform": "investing",
      "event_id": "inv__20251210233000",
      "original_id": "eventRowId_537547",
      "event_date": "2025-12-10",
      "event_time": "23:30",
      "event_datetime": "2025/12/10 23:30:00",
      "title": "美国当周EIA精炼油库存变动(桶)",
      "content": "前值: 2.059M",
      "category": null,
      "importance": 1,
      "country": "美国",
      "city": null,
      "stocks": [],
      "concepts": [],
      "themes": [],
      "data_status": "ACTIVE",
      "is_new": false,
      "discovery_date": "2025-12-09",
      "raw_data": {
        "event_id": "eventRowId_537547",
        "event_attr_id": "",
        "datetime": "2025/12/10 23:30:00",
        "time": "23:30",
        "country": "美国",
        "importance": 1,
        "event_name": "美国当周EIA精炼油库存变动(桶)",
        "previous": "2.059M"
      },
      "created_at": "2025-12-09T00:54:35.560610"
    },
    {
      "platform": "investing",
      "event_id": "inv__20251210233000",
      "original_id": "eventRowId_537548",
      "event_date": "2025-12-10",
      "event_time": "23:30",
      "event_datetime": "2025/12/10 23:30:00",
      "title": "美国当周EIA汽油产量变动(桶)",
      "content": "前值: 0.197M",
      "category": null,
      "importance": 1,
      "country": "美国",
      "city": null,
      "stocks": [],
      "concepts": [],
      "themes": [],
      "data_status": "ACTIVE",
      "is_new": false,
      "discovery_date": "2025-12-09",
      "raw_data": {
        "event_id": "eventRowId_537548",
        "event_attr_id": "",
        "datetime": "2025/12/10 23:30:00",
        "time": "23:30",
        "country": "美国",
        "importance": 1,
        "event_name": "美国当周EIA汽油产量变动(桶)",
        "previous": "0.197M"
      },
      "created_at": "2025-12-09T00:54:35.560730"
    },
    {
      "platform": "investing",
      "event_id": "inv__20251210233000",
      "original_id": "eventRowId_537549",
      "event_date": "2025-12-10",
      "event_time": "23:30",
      "event_datetime": "2025/12/10 23:30:00",
      "title": "美国当周EIA取暖油库存变动(桶)",
      "content": "前值: -0.293M",
      "category": null,
      "importance": 1,
      "country": "美国",
      "city": null,
      "stocks": [],
      "concepts": [],
      "themes": [],
      "data_status": "ACTIVE",
      "is_new": false,
      "discovery_date": "2025-12-09",
      "raw_data": {
        "event_id": "eventRowId_537549",
        "event_attr_id": "",
        "datetime": "2025/12/10 23:30:00",
        "time": "23:30",
        "country": "美国",
        "importance": 1,
        "event_name": "美国当周EIA取暖油库存变动(桶)",
        "previous": "-0.293M"
      },
      "created_at": "2025-12-09T00:54:35.560852"
    },
    {
      "platform": "investing",
      "event_id": "inv__20251210233000",
      "original_id": "eventRowId_537539",
      "event_date": "2025-12-10",
      "event_time": "23:30",
      "event_datetime": "2025/12/10 23:30:00",
      "title": "美国当周EIA精炼厂设备利用率变动 (每周)",
      "content": "前值: 1.8%",
      "category": null,
      "importance": 1,
      "country": "美国",
      "city": null,
      "stocks": [],
      "concepts": [],
      "themes": [],
      "data_status": "ACTIVE",
      "is_new": false,
      "discovery_date": "2025-12-09",
      "raw_data": {
        "event_id": "eventRowId_537539",
        "event_attr_id": "",
        "datetime": "2025/12/10 23:30:00",
        "time": "23:30",
        "country": "美国",
        "importance": 1,
        "event_name": "美国当周EIA精炼厂设备利用率变动 (每周)",
        "previous": "1.8%"
      },
      "created_at": "2025-12-09T00:54:35.560974"
    },
    {
      "platform": "investing",
      "event_id": "inv__20251210233000",
      "original_id": "eventRowId_537544",
      "event_date": "2025-12-10",
      "event_time": "23:30",
      "event_datetime": "2025/12/10 23:30:00",
      "title": "美国EIA汽油库存变动(桶)",
      "content": "前值: 4.518M",
      "category": null,
      "importance": 1,
      "country": "美国",
      "city": null,
      "stocks": [],
      "concepts": [],
      "themes": [],
      "data_status": "ACTIVE",
      "is_new": false,
      "discovery_date": "2025-12-09",
      "raw_data": {
        "event_id": "eventRowId_537544",
        "event_attr_id": "",
        "datetime": "2025/12/10 23:30:00",
        "time": "23:30",
        "country": "美国",
        "importance": 1,
        "event_name": "美国EIA汽油库存变动(桶)",
        "previous": "4.518M"
      },
      "created_at": "2025-12-09T00:54:35.561120"
    },
    {
      "platform": "investing",
      "event_id": "inv__20251210233000",
      "original_id": "eventRowId_537431",
      "event_date": "2025-12-10",
      "event_time": "23:30",
      "event_datetime": "2025/12/10 23:30:00",
      "title": "加拿大央行新闻发布会",
      "content": null,
      "category": null,
      "importance": 2,
      "country": "加拿大",
      "city": null,
      "stocks": [],
      "concepts": [],
      "themes": [],
      "data_status": "ACTIVE",
      "is_new": false,
      "discovery_date": "2025-12-09",
      "raw_data": {
        "event_id": "eventRowId_537431",
        "event_attr_id": "",
        "datetime": "2025/12/10 23:30:00",
        "time": "23:30",
        "country": "加拿大",
        "importance": 2,
        "event_name": "加拿大央行新闻发布会"
      },
      "created_at": "2025-12-09T00:54:35.561268"
    },
    {
      "platform": "eastmoney",
      "event_id": "em_jjsj_20251210000000_325236540167229179",
      "original_id": "2025-12-10 00:00:00_美国：预测年度:大豆:产量(报告期:2025年12月)",
      "event_date": "2025-12-10",
      "event_time": null,
      "event_datetime": "2025-12-10 00:00:00",
      "title": "美国：预测年度:大豆:产量(报告期:2025年12月)",
      "content": null,
      "category": "经济数据",
      "importance": 4,
      "country": "美国",
      "city": null,
      "stocks": [],
      "concepts": [],
      "themes": [],
      "data_status": "ACTIVE",
      "is_new": false,
      "discovery_date": "2025-12-09",
      "raw_data": {
        "Name": "美国：预测年度:大豆:产量(报告期:2025年12月)",
        "City": "美国"
      },
      "created_at": "2025-12-09T00:54:40.280315"
    },
    {
      "platform": "eastmoney",
      "event_id": "em_jjsj_20251210000000_-8054253513069042355",
      "original_id": "2025-12-10 00:00:00_美国：预测年度:玉米:产量(报告期:2025年12月)",
      "event_date": "2025-12-10",
      "event_time": null,
      "event_datetime": "2025-12-10 00:00:00",
      "title": "美国：预测年度:玉米:产量(报告期:2025年12月)",
      "content": null,
      "category": "经济数据",
      "importance": 4,
      "country": "美国",
      "city": null,
      "stocks": [],
      "concepts": [],
      "themes": [],
      "data_status": "ACTIVE",
      "is_new": false,
      "discovery_date": "2025-12-09",
      "raw_data": {
        "Name": "美国：预测年度:玉米:产量(报告期:2025年12月)",
        "City": "美国"
      },
      "created_at": "2025-12-09T00:54:40.280323"
    },
    {
      "platform": "eastmoney",
      "event_id": "em_jjsj_20251210000000_5475415122859028919",
      "original_id": "2025-12-10 00:00:00_美国：预测年度:棉花:产量(报告期:2025年12月)",
      "event_date": "2025-12-10",
      "event_time": null,
      "event_datetime": "2025-12-10 00:00:00",
      "title": "美国：预测年度:棉花:产量(报告期:2025年12月)",
      "content": null,
      "category": "经济数据",
      "importance": 4,
      "country": "美国",
      "city": null,
      "stocks": [],
      "concepts": [],
      "themes": [],
      "data_status": "ACTIVE",
      "is_new": false,
      "discovery_date": "2025-12-09",
      "raw_data": {
        "Name": "美国：预测年度:棉花:产量(报告期:2025年12月)",
        "City": "美国"
      },
      "created_at": "2025-12-09T00:54:40.280330"
    },
    {
      "platform": "eastmoney",
      "event_id": "em_jjsj_20251210000000_-1951424291848946513",
      "original_id": "2025-12-10 00:00:00_美国：预测年度:小麦:产量(报告期:2025年12月)",
      "event_date": "2025-12-10",
      "event_time": null,
      "event_datetime": "2025-12-10 00:00:00",
      "title": "美国：预测年度:小麦:产量(报告期:2025年12月)",
      "content": null,
      "category": "经济数据",
      "importance": 4,
      "country": "美国",
      "city": null,
      "stocks": [],
      "concepts": [],
      "themes": [],
      "data_status": "ACTIVE",
      "is_new": false,
      "discovery_date": "2025-12-09",
      "raw_data": {
        "Name": "美国：预测年度:小麦:产量(报告期:2025年12月)",
        "City": "美国"
      },
      "created_at": "2025-12-09T00:54:40.280338"
    },
    {
      "platform": "eastmoney",
      "event_id": "em_jjsj_20251210093000_1184937569450349604",
      "original_id": "2025-12-10 09:30:00_中国：CPI:累计同比(报告期:2025年11月)",
      "event_date": "2025-12-10",
      "event_time": "09:30:00",
      "event_datetime": "2025-12-10 09:30:00",
      "title": "中国：CPI:累计同比(报告期:2025年11月)",
      "content": null,
      "category": "经济数据",
      "importance": 4,
      "country": "中国",
      "city": null,
      "stocks": [],
      "concepts": [],
      "themes": [],
      "data_status": "ACTIVE",
      "is_new": false,
      "discovery_date": "2025-12-09",
      "raw_data": {
        "Name": "中国：CPI:累计同比(报告期:2025年11月)",
        "City": "中国"
      },
      "created_at": "2025-12-09T00:54:40.280346"
    },
    {
      "platform": "eastmoney",
      "event_id": "em_jjsj_20251210093000_-1373928835187842342",
      "original_id": "2025-12-10 09:30:00_中国：CPI:当月同比(报告期:2025年11月)",
      "event_date": "2025-12-10",
      "event_time": "09:30:00",
      "event_datetime": "2025-12-10 09:30:00",
      "title": "中国：CPI:当月同比(报告期:2025年11月)",
      "content": null,
      "category": "经济数据",
      "importance": 4,
      "country": "中国",
      "city": null,
      "stocks": [],
      "concepts": [],
      "themes": [],
      "data_status": "ACTIVE",
      "is_new": false,
      "discovery_date": "2025-12-09",
      "raw_data": {
        "Name": "中国：CPI:当月同比(报告期:2025年11月)",
        "City": "中国"
      },
      "created_at": "2025-12-09T00:54:40.280353"
    },
    {
      "platform": "eastmoney",
      "event_id": "em_jjsj_20251210093000_5177604572349081491",
      "original_id": "2025-12-10 09:30:00_中国：CPI:环比(报告期:2025年11月)",
      "event_date": "2025-12-10",
      "event_time": "09:30:00",
      "event_datetime": "2025-12-10 09:30:00",
      "title": "中国：CPI:环比(报告期:2025年11月)",
      "content": null,
      "category": "经济数据",
      "importance": 4,
      "country": "中国",
      "city": null,
      "stocks": [],
      "concepts": [],
      "themes": [],
      "data_status": "ACTIVE",
      "is_new": false,
      "discovery_date": "2025-12-09",
      "raw_data": {
        "Name": "中国：CPI:环比(报告期:2025年11月)",
        "City": "中国"
      },
      "created_at": "2025-12-09T00:54:40.280361"
    },
    {
      "platform": "eastmoney",
      "event_id": "em_jjsj_20251210093000_4706079986067087586",
      "original_id": "2025-12-10 09:30:00_中国：PPI:全部工业品:累计同比(报告期:2025年11月)",
      "event_date": "2025-12-10",
      "event_time": "09:30:00",
      "event_datetime": "2025-12-10 09:30:00",
      "title": "中国：PPI:全部工业品:累计同比(报告期:2025年11月)",
      "content": null,
      "category": "经济数据",
      "importance": 4,
      "country": "中国",
      "city": null,
      "stocks": [],
      "concepts": [],
      "themes": [],
      "data_status": "ACTIVE",
      "is_new": false,
      "discovery_date": "2025-12-09",
      "raw_data": {
        "Name": "中国：PPI:全部工业品:累计同比(报告期:2025年11月)",
        "City": "中国"
      },
      "created_at": "2025-12-09T00:54:40.280368"
    },
    {
      "platform": "eastmoney",
      "event_id": "em_jjsj_20251210093000_4212810049853453294",
      "original_id": "2025-12-10 09:30:00_中国：PPI:全部工业品:环比(报告期:2025年11月)",
      "event_date": "2025-12-10",
      "event_time": "09:30:00",
      "event_datetime": "2025-12-10 09:30:00",
      "title": "中国：PPI:全部工业品:环比(报告期:2025年11月)",
      "content": null,
      "category": "经济数据",
      "importance": 4,
      "country": "中国",
      "city": null,
      "stocks": [],
      "concepts": [],
      "themes": [],
      "data_status": "ACTIVE",
      "is_new": false,
      "discovery_date": "2025-12-09",
      "raw_data": {
        "Name": "中国：PPI:全部工业品:环比(报告期:2025年11月)",
        "City": "中国"
      },
      "created_at": "2025-12-09T00:54:40.280376"
    },
    {
      "platform": "eastmoney",
      "event_id": "em_jjsj_20251210093000_1925253669280911529",
      "original_id": "2025-12-10 09:30:00_中国：PPI:全部工业品:当月同比(报告期:2025年11月)",
      "event_date": "2025-12-10",
      "event_time": "09:30:00",
      "event_datetime": "2025-12-10 09:30:00",
      "title": "中国：PPI:全部工业品:当月同比(报告期:2025年11月)",
      "content": null,
      "category": "经济数据",
      "importance": 4,
      "country": "中国",
      "city": null,
      "stocks": [],
      "concepts": [],
      "themes": [],
      "data_status": "ACTIVE",
      "is_new": false,
      "discovery_date": "2025-12-09",
      "raw_data": {
        "Name": "中国：PPI:全部工业品:当月同比(报告期:2025年11月)",
        "City": "中国"
      },
      "created_at": "2025-12-09T00:54:40.280384"
    },
    {
      "platform": "eastmoney",
      "event_id": "em_jjsj_20251210160000_-5704732647041092060",
      "original_id": "2025-12-10 16:00:00_中国:M1:同比(报告期:2025年11月)",
      "event_date": "2025-12-10",
      "event_time": "16:00:00",
      "event_datetime": "2025-12-10 16:00:00",
      "title": "中国:M1:同比(报告期:2025年11月)",
      "content": null,
      "category": "经济数据",
      "importance": 4,
      "country": "中国",
      "city": null,
      "stocks": [],
      "concepts": [],
      "themes": [],
      "data_status": "ACTIVE",
      "is_new": false,
      "discovery_date": "2025-12-09",
      "raw_data": {
        "Name": "中国:M1:同比(报告期:2025年11月)",
        "City": "中国"
      },
      "created_at": "2025-12-09T00:54:40.280392"
    },
    {
      "platform": "eastmoney",
      "event_id": "em_jjsj_20251210160000_1012521815176921957",
      "original_id": "2025-12-10 16:00:00_中国:M0:同比(报告期:2025年11月)",
      "event_date": "2025-12-10",
      "event_time": "16:00:00",
      "event_datetime": "2025-12-10 16:00:00",
      "title": "中国:M0:同比(报告期:2025年11月)",
      "content": null,
      "category": "经济数据",
      "importance": 4,
      "country": "中国",
      "city": null,
      "stocks": [],
      "concepts": [],
      "themes": [],
      "data_status": "ACTIVE",
      "is_new": false,
      "discovery_date": "2025-12-09",
      "raw_data": {
        "Name": "中国:M0:同比(报告期:2025年11月)",
        "City": "中国"
      },
      "created_at": "2025-12-09T00:54:40.280400"
    },
    {
      "platform": "eastmoney",
      "event_id": "em_jjsj_20251210200000_-8157310723754652929",
      "original_id": "2025-12-10 20:00:00_巴西：CPI：同比(报告期:2025年11月)",
      "event_date": "2025-12-10",
      "event_time": "20:00:00",
      "event_datetime": "2025-12-10 20:00:00",
      "title": "巴西：CPI：同比(报告期:2025年11月)",
      "content": null,
      "category": "经济数据",
      "importance": 4,
      "country": "巴西",
      "city": null,
      "stocks": [],
      "concepts": [],
      "themes": [],
      "data_status": "ACTIVE",
      "is_new": false,
      "discovery_date": "2025-12-09",
      "raw_data": {
        "Name": "巴西：CPI：同比(报告期:2025年11月)",
        "City": "巴西"
      },
      "created_at": "2025-12-09T00:54:40.280409"
    },
    {
      "platform": "eastmoney",
      "event_id": "em_jjsj_20251210213000_-5309096091507987928",
      "original_id": "2025-12-10 21:30:00_美国：核心CPI：当月同比(报告期:2025年11月)",
      "event_date": "2025-12-10",
      "event_time": "21:30:00",
      "event_datetime": "2025-12-10 21:30:00",
      "title": "美国：核心CPI：当月同比(报告期:2025年11月)",
      "content": null,
      "category": "经济数据",
      "importance": 4,
      "country": "美国",
      "city": null,
      "stocks": [],
      "concepts": [],
      "themes": [],
      "data_status": "ACTIVE",
      "is_new": false,
      "discovery_date": "2025-12-09",
      "raw_data": {
        "Name": "美国：核心CPI：当月同比(报告期:2025年11月)",
        "City": "美国"
      },
      "created_at": "2025-12-09T00:54:40.280417"
    },
    {
      "platform": "eastmoney",
      "event_id": "em_jjsj_20251210213000_1287852097238108898",
      "original_id": "2025-12-10 21:30:00_美国：CPI：当月同比(报告期:2025年11月)",
      "event_date": "2025-12-10",
      "event_time": "21:30:00",
      "event_datetime": "2025-12-10 21:30:00",
      "title": "美国：CPI：当月同比(报告期:2025年11月)",
      "content": null,
      "category": "经济数据",
      "importance": 4,
      "country": "美国",
      "city": null,
      "stocks": [],
      "concepts": [],
      "themes": [],
      "data_status": "ACTIVE",
      "is_new": false,
      "discovery_date": "2025-12-09",
      "raw_data": {
        "Name": "美国：CPI：当月同比(报告期:2025年11月)",
        "City": "美国"
      },
      "created_at": "2025-12-09T00:54:40.280425"
    },
    {
      "platform": "eastmoney",
      "event_id": "em_jjsj_20251210213000_7835193862880440766",
      "original_id": "2025-12-10 21:30:00_美国：核心CPI：季调：当月同比(报告期:2025年11月)",
      "event_date": "2025-12-10",
      "event_time": "21:30:00",
      "event_datetime": "2025-12-10 21:30:00",
      "title": "美国：核心CPI：季调：当月同比(报告期:2025年11月)",
      "content": null,
      "category": "经济数据",
      "importance": 4,
      "country": "美国",
      "city": null,
      "stocks": [],
      "concepts": [],
      "themes": [],
      "data_status": "ACTIVE",
      "is_new": false,
      "discovery_date": "2025-12-09",
      "raw_data": {
        "Name": "美国：核心CPI：季调：当月同比(报告期:2025年11月)",
        "City": "美国"
      },
      "created_at": "2025-12-09T00:54:40.280433"
    },
    {
      "platform": "eastmoney",
      "event_id": "em_jjsj_20251210213000_-4729484428920832399",
      "original_id": "2025-12-10 21:30:00_美国：核心CPI(报告期:2025年11月)",
      "event_date": "2025-12-10",
      "event_time": "21:30:00",
      "event_datetime": "2025-12-10 21:30:00",
      "title": "美国：核心CPI(报告期:2025年11月)",
      "content": null,
      "category": "经济数据",
      "importance": 4,
      "country": "美国",
      "city": null,
      "stocks": [],
      "concepts": [],
      "themes": [],
      "data_status": "ACTIVE",
      "is_new": false,
      "discovery_date": "2025-12-09",
      "raw_data": {
        "Name": "美国：核心CPI(报告期:2025年11月)",
        "City": "美国"
      },
      "created_at": "2025-12-09T00:54:40.280440"
    },
    {
      "platform": "eastmoney",
      "event_id": "em_jjsj_20251210213000_-8500530643972532968",
      "original_id": "2025-12-10 21:30:00_美国：CPI：季调：环比(报告期:2025年11月)",
      "event_date": "2025-12-10",
      "event_time": "21:30:00",
      "event_datetime": "2025-12-10 21:30:00",
      "title": "美国：CPI：季调：环比(报告期:2025年11月)",
      "content": null,
      "category": "经济数据",
      "importance": 4,
      "country": "美国",
      "city": null,
      "stocks": [],
      "concepts": [],
      "themes": [],
      "data_status": "ACTIVE",
      "is_new": false,
      "discovery_date": "2025-12-09",
      "raw_data": {
        "Name": "美国：CPI：季调：环比(报告期:2025年11月)",
        "City": "美国"
      },
      "created_at": "2025-12-09T00:54:40.280447"
    },
    {
      "platform": "eastmoney",
      "event_id": "em_jjsj_20251210213000_5340915132925828481",
      "original_id": "2025-12-10 21:30:00_美国：核心CPI：季调：环比(报告期:2025年11月)",
      "event_date": "2025-12-10",
      "event_time": "21:30:00",
      "event_datetime": "2025-12-10 21:30:00",
      "title": "美国：核心CPI：季调：环比(报告期:2025年11月)",
      "content": null,
      "category": "经济数据",
      "importance": 4,
      "country": "美国",
      "city": null,
      "stocks": [],
      "concepts": [],
      "themes": [],
      "data_status": "ACTIVE",
      "is_new": false,
      "discovery_date": "2025-12-09",
      "raw_data": {
        "Name": "美国：核心CPI：季调：环比(报告期:2025年11月)",
        "City": "美国"
      },
      "created_at": "2025-12-09T00:54:40.280455"
    },
    {
      "platform": "eastmoney",
      "event_id": "em_jjsj_20251210224500_-6001756990413739709",
      "original_id": "2025-12-10 22:45:00_加拿大：央行公布利率决议(报告期:2025年12月)",
      "event_date": "2025-12-10",
      "event_time": "22:45:00",
      "event_datetime": "2025-12-10 22:45:00",
      "title": "加拿大：央行公布利率决议(报告期:2025年12月)",
      "content": null,
      "category": "经济数据",
      "importance": 4,
      "country": "加拿大",
      "city": null,
      "stocks": [],
      "concepts": [],
      "themes": [],
      "data_status": "ACTIVE",
      "is_new": false,
      "discovery_date": "2025-12-09",
      "raw_data": {
        "Name": "加拿大：央行公布利率决议(报告期:2025年12月)",
        "City": "加拿大"
      },
      "created_at": "2025-12-09T00:54:40.280463"
    },
    {
      "platform": "eastmoney",
      "event_id": "em_jjsj_20251210233000_-8793962492826699358",
      "original_id": "2025-12-10 23:30:00_美国EIA俄克拉荷马州库欣原油库存:当周值(报告期:2025年12月)",
      "event_date": "2025-12-10",
      "event_time": "23:30:00",
      "event_datetime": "2025-12-10 23:30:00",
      "title": "美国EIA俄克拉荷马州库欣原油库存:当周值(报告期:2025年12月)",
      "content": null,
      "category": "经济数据",
      "importance": 4,
      "country": "美国",
      "city": null,
      "stocks": [],
      "concepts": [],
      "themes": [],
      "data_status": "ACTIVE",
      "is_new": false,
      "discovery_date": "2025-12-09",
      "raw_data": {
        "Name": "美国EIA俄克拉荷马州库欣原油库存:当周值(报告期:2025年12月)",
        "City": "美国"
      },
      "created_at": "2025-12-09T00:54:40.280471"
    },
    {
      "platform": "eastmoney",
      "event_id": "em_jjsj_20251210233000_-3323128477285803278",
      "original_id": "2025-12-10 23:30:00_美国DOE燃料乙醇总产量:当周值(报告期:2025年12月)",
      "event_date": "2025-12-10",
      "event_time": "23:30:00",
      "event_datetime": "2025-12-10 23:30:00",
      "title": "美国DOE燃料乙醇总产量:当周值(报告期:2025年12月)",
      "content": null,
      "category": "经济数据",
      "importance": 4,
      "country": "美国",
      "city": null,
      "stocks": [],
      "concepts": [],
      "themes": [],
      "data_status": "ACTIVE",
      "is_new": false,
      "discovery_date": "2025-12-09",
      "raw_data": {
        "Name": "美国DOE燃料乙醇总产量:当周值(报告期:2025年12月)",
        "City": "美国"
      },
      "created_at": "2025-12-09T00:54:40.280479"
    },
    {
      "platform": "eastmoney",
      "event_id": "em_jjsj_20251210233000_9031175774163433016",
      "original_id": "2025-12-10 23:30:00_美国EIA原油库存:变动值(报告期:2025年12月)",
      "event_date": "2025-12-10",
      "event_time": "23:30:00",
      "event_datetime": "2025-12-10 23:30:00",
      "title": "美国EIA原油库存:变动值(报告期:2025年12月)",
      "content": null,
      "category": "经济数据",
      "importance": 4,
      "country": "美国",
      "city": null,
      "stocks": [],
      "concepts": [],
      "themes": [],
      "data_status": "ACTIVE",
      "is_new": false,
      "discovery_date": "2025-12-09",
      "raw_data": {
        "Name": "美国EIA原油库存:变动值(报告期:2025年12月)",
        "City": "美国"
      },
      "created_at": "2025-12-09T00:54:40.280487"
    },
    {
      "platform": "eastmoney",
      "event_id": "em_jjsj_20251210233000_832087632417124324",
      "original_id": "2025-12-10 23:30:00_美国EIA汽油库存:变动值(报告期:2025年12月)",
      "event_date": "2025-12-10",
      "event_time": "23:30:00",
      "event_datetime": "2025-12-10 23:30:00",
      "title": "美国EIA汽油库存:变动值(报告期:2025年12月)",
      "content": null,
      "category": "经济数据",
      "importance": 4,
      "country": "美国",
      "city": null,
      "stocks": [],
      "concepts": [],
      "themes": [],
      "data_status": "ACTIVE",
      "is_new": false,
      "discovery_date": "2025-12-09",
      "raw_data": {
        "Name": "美国EIA汽油库存:变动值(报告期:2025年12月)",
        "City": "美国"
      },
      "created_at": "2025-12-09T00:54:40.280494"
    },
    {
      "platform": "eastmoney",
      "event_id": "em_jjsj_20251210233000_-6836182366068692210",
      "original_id": "2025-12-10 23:30:00_美国DOE燃料乙醇总库存:当周值(报告期:2025年12月)",
      "event_date": "2025-12-10",
      "event_time": "23:30:00",
      "event_datetime": "2025-12-10 23:30:00",
      "title": "美国DOE燃料乙醇总库存:当周值(报告期:2025年12月)",
      "content": null,
      "category": "经济数据",
      "importance": 4,
      "country": "美国",
      "city": null,
      "stocks": [],
      "concepts": [],
      "themes": [],
      "data_status": "ACTIVE",
      "is_new": false,
      "discovery_date": "2025-12-09",
      "raw_data": {
        "Name": "美国DOE燃料乙醇总库存:当周值(报告期:2025年12月)",
        "City": "美国"
      },
      "created_at": "2025-12-09T00:54:40.280502"
    },
    {
      "platform": "eastmoney",
      "event_id": "em_jjsj_20251210233000_-6953872906645002841",
      "original_id": "2025-12-10 23:30:00_美国DOE原油引申需求:当周值(报告期:2025年12月)",
      "event_date": "2025-12-10",
      "event_time": "23:30:00",
      "event_datetime": "2025-12-10 23:30:00",
      "title": "美国DOE原油引申需求:当周值(报告期:2025年12月)",
      "content": null,
      "category": "经济数据",
      "importance": 4,
      "country": "美国",
      "city": null,
      "stocks": [],
      "concepts": [],
      "themes": [],
      "data_status": "ACTIVE",
      "is_new": false,
      "discovery_date": "2025-12-09",
      "raw_data": {
        "Name": "美国DOE原油引申需求:当周值(报告期:2025年12月)",
        "City": "美国"
      },
      "created_at": "2025-12-09T00:54:40.280510"
    },
    {
      "platform": "eastmoney",
      "event_id": "em_jjsj_20251210233000_1237344443255474523",
      "original_id": "2025-12-10 23:30:00_美国DOE蒸馏油引申需求:当周值(报告期:2025年12月)",
      "event_date": "2025-12-10",
      "event_time": "23:30:00",
      "event_datetime": "2025-12-10 23:30:00",
      "title": "美国DOE蒸馏油引申需求:当周值(报告期:2025年12月)",
      "content": null,
      "category": "经济数据",
      "importance": 4,
      "country": "美国",
      "city": null,
      "stocks": [],
      "concepts": [],
      "themes": [],
      "data_status": "ACTIVE",
      "is_new": false,
      "discovery_date": "2025-12-09",
      "raw_data": {
        "Name": "美国DOE蒸馏油引申需求:当周值(报告期:2025年12月)",
        "City": "美国"
      },
      "created_at": "2025-12-09T00:54:40.280518"
    },
    {
      "platform": "eastmoney",
      "event_id": "em_jjsj_20251210233000_8524630511122751201",
      "original_id": "2025-12-10 23:30:00_美国DOE汽油引申需求:当周值(报告期:2025年12月)",
      "event_date": "2025-12-10",
      "event_time": "23:30:00",
      "event_datetime": "2025-12-10 23:30:00",
      "title": "美国DOE汽油引申需求:当周值(报告期:2025年12月)",
      "content": null,
      "category": "经济数据",
      "importance": 4,
      "country": "美国",
      "city": null,
      "stocks": [],
      "concepts": [],
      "themes": [],
      "data_status": "ACTIVE",
      "is_new": false,
      "discovery_date": "2025-12-09",
      "raw_data": {
        "Name": "美国DOE汽油引申需求:当周值(报告期:2025年12月)",
        "City": "美国"
      },
      "created_at": "2025-12-09T00:54:40.280526"
    },
    {
      "platform": "eastmoney",
      "event_id": "em_jjsj_20251210233000_2604860917153414782",
      "original_id": "2025-12-10 23:30:00_美国EIA精炼油库存:变动值(报告期:2025年12月)",
      "event_date": "2025-12-10",
      "event_time": "23:30:00",
      "event_datetime": "2025-12-10 23:30:00",
      "title": "美国EIA精炼油库存:变动值(报告期:2025年12月)",
      "content": null,
      "category": "经济数据",
      "importance": 4,
      "country": "美国",
      "city": null,
      "stocks": [],
      "concepts": [],
      "themes": [],
      "data_status": "ACTIVE",
      "is_new": false,
      "discovery_date": "2025-12-09",
      "raw_data": {
        "Name": "美国EIA精炼油库存:变动值(报告期:2025年12月)",
        "City": "美国"
      },
      "created_at": "2025-12-09T00:54:40.280534"
    },
    {
      "platform": "eastmoney",
      "event_id": "em_jjsj_20251210233000_4177557097621160609",
      "original_id": "2025-12-10 23:30:00_美国:当周EIA车用汽油总产量引伸需求数据(报告期:2025年12月)",
      "event_date": "2025-12-10",
      "event_time": "23:30:00",
      "event_datetime": "2025-12-10 23:30:00",
      "title": "美国:当周EIA车用汽油总产量引伸需求数据(报告期:2025年12月)",
      "content": null,
      "category": "经济数据",
      "importance": 4,
      "country": "美国",
      "city": null,
      "stocks": [],
      "concepts": [],
      "themes": [],
      "data_status": "ACTIVE",
      "is_new": false,
      "discovery_date": "2025-12-09",
      "raw_data": {
        "Name": "美国:当周EIA车用汽油总产量引伸需求数据(报告期:2025年12月)",
        "City": "美国"
      },
      "created_at": "2025-12-09T00:54:40.280541"
    },
    {
      "platform": "eastmoney",
      "event_id": "em_hyhy_10866884",
      "original_id": "10866884",
      "event_date": "2025-12-10",
      "event_time": null,
      "event_datetime": null,
      "title": "第二十届中国IDC产业年度大典",
      "content": "本次大会标志着中国IDC产业二十年发展的关键转折点,全面开启算力基础设施的破界重塑时代。过去二十年,IDC产业从简单的机房托管走向云网融合,从基础设施服务迈向算力生态运营,如今正面临前所未有的底层架构重构。AI大模型的爆发式增长彻底打破了传统边界:单机柜功率大幅飙升、万卡级超大集群对供电、散热、互联提出颠覆性要求、算力与电力从各自独立走向深度耦合,绿电直连、储能配套、虚拟电厂等日益受到行业关注、商业模式从资源售卖转向能力服务,算力即服务正重构产业价值链。本届大会以“重塑算力破界而生”为主题,聚焦生态协同、技术创新、应用融合、可持续发展四大维度,汇聚全球算力产业链核心力量,共同探索AI算力、算电协同、国产化生态、集群建设、绿色能源技术创新、高密度液冷、HVDC供电等算力产业关键领域发展与突破,携手打造智能时代的绿色算力底座,引领产业迈向高质量发展新征程。",
      "category": "行业会议",
      "importance": 3,
      "country": "中国",
      "city": "北京市",
      "stocks": [],
      "concepts": [],
      "themes": [],
      "data_status": "ACTIVE",
      "is_new": false,
      "discovery_date": "2025-12-09",
      "raw_data": {
        "fe_code": "10866884",
        "fe_name": "第二十届中国IDC产业年度大典",
        "start_date": "2025-12-10",
        "end_date": "2025-12-11",
        "fe_type": "行业会议",
        "sponsor": "中国IDC产业年度大典组委会,数字基础设施科技展(DITExpo)",
        "city": "北京市",
        "content": "本次大会标志着中国IDC产业二十年发展的关键转折点,全面开启算力基础设施的破界重塑时代。过去二十年,IDC产业从简单的机房托管走向云网融合,从基础设施服务迈向算力生态运营,如今正面临前所未有的底层架构重构。AI大模型的爆发式增长彻底打破了传统边界:单机柜功率大幅飙升、万卡级超大集群对供电、散热、互联提出颠覆性要求、算力与电力从各自独立走向深度耦合,绿电直连、储能配套、虚拟电厂等日益受到行业关注、商业模式从资源售卖转向能力服务,算力即服务正重构产业价值链。本届大会以“重塑算力破界而生”为主题,聚焦生态协同、技术创新、应用融合、可持续发展四大维度,汇聚全球算力产业链核心力量,共同探索AI算力、算电协同、国产化生态、集群建设、绿色能源技术创新、高密度液冷、HVDC供电等算力产业关键领域发展与突破,携手打造智能时代的绿色算力底座,引领产业迈向高质量发展新征程。"
      },
      "created_at": "2025-12-09T00:54:40.282010"
    },
    {
      "platform": "eastmoney",
      "event_id": "em_hyhy_10867067",
      "original_id": "10867067",
      "event_date": "2025-12-10",
      "event_time": null,
      "event_datetime": null,
      "title": "2025中国铂族金属市场年会",
      "content": "为聚焦金融强国战略下铂族金属市场的新机遇,共同探索高质量发展路径,受三亚市投资促进局邀请,中国黄金协会、世界铂金投资协会定于12月10日在海南三亚召开“2025中国铂族金属市场年会”。现将有关事项通知如下:一、会议内容会议将立足国家产融结合战略,重点研讨铂族金属市场动态与全球经济格局、产业政策调整及技术创新趋势。同时,结合海南自贸港封关运作的关键节点,积极探寻产业与政策红利的对接路径,为铂族金属产业开拓发展新机遇、新空间。",
      "category": "行业会议",
      "importance": 3,
      "country": "中国",
      "city": "三亚市",
      "stocks": [],
      "concepts": [],
      "themes": [],
      "data_status": "ACTIVE",
      "is_new": true,
      "discovery_date": "2025-12-09",
      "raw_data": {
        "fe_code": "10867067",
        "fe_name": "2025中国铂族金属市场年会",
        "start_date": "2025-12-10",
        "end_date": "2025-12-10",
        "fe_type": "行业会议",
        "sponsor": null,
        "city": "三亚市",
        "content": "为聚焦金融强国战略下铂族金属市场的新机遇,共同探索高质量发展路径,受三亚市投资促进局邀请,中国黄金协会、世界铂金投资协会定于12月10日在海南三亚召开“2025中国铂族金属市场年会”。现将有关事项通知如下:一、会议内容会议将立足国家产融结合战略,重点研讨铂族金属市场动态与全球经济格局、产业政策调整及技术创新趋势。同时,结合海南自贸港封关运作的关键节点,积极探寻产业与政策红利的对接路径,为铂族金属产业开拓发展新机遇、新空间。"
      },
      "created_at": "2025-12-09T00:54:40.282018"
    }
  ]
}